<?xml version='1.0' encoding='UTF-8'?>
<!DOCTYPE Bundle PUBLIC "sailpoint.dtd" "sailpoint.dtd">
<Bundle   name="Local Administrator Demo Server" type="it">
  <Description>This role gives the user full administrative rights to a server in the demo environment</Description>
  <Inheritance>
    <Reference class="sailpoint.object.Bundle"  name="Nordea Access"/>
  </Inheritance>
  <Owner>
    <Reference class="sailpoint.object.Identity"  name="spadmin"/>
  </Owner>
  <Profiles>
    <Profile   name="ONEADR">
      <ApplicationRef>
        <Reference class="sailpoint.object.Application"  name="ONEADR"/>
      </ApplicationRef>
      <Constraints>
        <CompositeFilter operation="OR">
          <Filter ignoreCase="true" operation="CONTAINS_ALL" property="memberOf">
            <Value>
              <List>
                <String>CN=sec-CMCC-CMA1GE0026 local admin,OU=CMCC Ser Local Adm,OU=Groups,OU=CMCC,OU=_CORP,DC=oneadr,DC=net</String>
              </List>
            </Value>
          </Filter>
          <Filter ignoreCase="true" operation="CONTAINS_ALL" property="memberOf">
            <Value>
              <List>
                <String>CN=sec-CMCC-CMA1GE0027 local admin,OU=CMCC Ser Local Adm,OU=Groups,OU=CMCC,OU=_CORP,DC=oneadr,DC=net</String>
              </List>
            </Value>
          </Filter>
          <Filter ignoreCase="true" operation="CONTAINS_ALL" property="memberOf">
            <Value>
              <List>
                <String>CN=sec-CMCC-CMA1CS0270 local admin,OU=CMCC Ser Local Adm,OU=Groups,OU=CMCC,OU=_CORP,DC=oneadr,DC=net</String>
              </List>
            </Value>
          </Filter>
          <Filter ignoreCase="true" operation="CONTAINS_ALL" property="memberOf">
            <Value>
              <List>
                <String>CN=sec-CMCC-CMA1CS0271 local admin,OU=CMCC Ser Local Adm,OU=Groups,OU=CMCC,OU=_CORP,DC=oneadr,DC=net</String>
              </List>
            </Value>
          </Filter>
          <Filter ignoreCase="true" operation="CONTAINS_ALL" property="memberOf">
            <Value>
              <List>
                <String>CN=sec-CMCC-CMA1CS0272 local admin,OU=CMCC Ser Local Adm,OU=Groups,OU=CMCC,OU=_CORP,DC=oneadr,DC=net</String>
              </List>
            </Value>
          </Filter>
          <Filter ignoreCase="true" operation="CONTAINS_ALL" property="memberOf">
            <Value>
              <List>
                <String>CN=sec-CMCC-CMA1CS0269 local admin,OU=CMCC Ser Local Adm,OU=Groups,OU=CMCC,OU=_CORP,DC=oneadr,DC=net</String>
              </List>
            </Value>
          </Filter>
          <Filter ignoreCase="true" operation="CONTAINS_ALL" property="memberOf">
            <Value>
              <List>
                <String>CN=sec-CMCC-CMA1CS0376 local admin,OU=CMCC Ser Local Adm,OU=Groups,OU=CMCC,OU=_CORP,DC=oneadr,DC=net</String>
              </List>
            </Value>
          </Filter>
          <Filter ignoreCase="true" operation="CONTAINS_ALL" property="memberOf">
            <Value>
              <List>
                <String>CN=sec-CMCC-CMA1CS0194 local admin,OU=CMCC Ser Local Adm,OU=Groups,OU=CMCC,OU=_CORP,DC=oneadr,DC=net</String>
              </List>
            </Value>
          </Filter>
          <Filter ignoreCase="true" operation="CONTAINS_ALL" property="memberOf">
            <Value>
              <List>
                <String>CN=sec-CMCC-CMA1CS0342 local admin,OU=CMCC Ser Local Adm,OU=Groups,OU=CMCC,OU=_CORP,DC=oneadr,DC=net</String>
              </List>
            </Value>
          </Filter>
          <Filter ignoreCase="true" operation="CONTAINS_ALL" property="memberOf">
            <Value>
              <List>
                <String>CN=sec-CMCC-CMA1CS0344 local admin,OU=CMCC Ser Local Adm,OU=Groups,OU=CMCC,OU=_CORP,DC=oneadr,DC=net</String>
              </List>
            </Value>
          </Filter>
          <Filter ignoreCase="true" operation="CONTAINS_ALL" property="memberOf">
            <Value>
              <List>
                <String>CN=sec-CMCC-CMA1CS0343 local admin,OU=CMCC Ser Local Adm,OU=Groups,OU=CMCC,OU=_CORP,DC=oneadr,DC=net</String>
              </List>
            </Value>
          </Filter>
          <Filter ignoreCase="true" operation="CONTAINS_ALL" property="memberOf">
            <Value>
              <List>
                <String>CN=sec-CMCC-CMA1CS0377 local admin,OU=CMCC Ser Local Adm,OU=Groups,OU=CMCC,OU=_CORP,DC=oneadr,DC=net</String>
              </List>
            </Value>
          </Filter>
          <Filter ignoreCase="true" operation="CONTAINS_ALL" property="memberOf">
            <Value>
              <List>
                <String>CN=sec-CMCC-CMA1CS0375 local admin,OU=CMCC Ser Local Adm,OU=Groups,OU=CMCC,OU=_CORP,DC=oneadr,DC=net</String>
              </List>
            </Value>
          </Filter>
          <Filter ignoreCase="true" operation="CONTAINS_ALL" property="memberOf">
            <Value>
              <List>
                <String>CN=sec-CMCC-CMA1CS0384 local admin,OU=CMCC Ser Local Adm,OU=Groups,OU=CMCC,OU=_CORP,DC=oneadr,DC=net</String>
              </List>
            </Value>
          </Filter>
          <Filter ignoreCase="true" operation="CONTAINS_ALL" property="memberOf">
            <Value>
              <List>
                <String>CN=sec-CMCC-CMA1CS0164 local admin,OU=CMCC Ser Local Adm,OU=Groups,OU=CMCC,OU=_CORP,DC=oneadr,DC=net</String>
              </List>
            </Value>
          </Filter>
          <Filter ignoreCase="true" operation="CONTAINS_ALL" property="memberOf">
            <Value>
              <List>
                <String>CN=sec-CMCC-CMA1TS0038 local admin,OU=CMCC Ser Local Adm,OU=Groups,OU=CMCC,OU=_CORP,DC=oneadr,DC=net</String>
              </List>
            </Value>
          </Filter>
          <Filter ignoreCase="true" operation="CONTAINS_ALL" property="memberOf">
            <Value>
              <List>
                <String>CN=sec-CMCC-CMA1TS0039 local admin,OU=CMCC Ser Local Adm,OU=Groups,OU=CMCC,OU=_CORP,DC=oneadr,DC=net</String>
              </List>
            </Value>
          </Filter>
          <Filter ignoreCase="true" operation="CONTAINS_ALL" property="memberOf">
            <Value>
              <List>
                <String>CN=sec-CMCC-CMA1TS0040 local admin,OU=CMCC Ser Local Adm,OU=Groups,OU=CMCC,OU=_CORP,DC=oneadr,DC=net</String>
              </List>
            </Value>
          </Filter>
          <Filter ignoreCase="true" operation="CONTAINS_ALL" property="memberOf">
            <Value>
              <List>
                <String>CN=sec-CMCC-CMA1TS0041 local admin,OU=CMCC Ser Local Adm,OU=Groups,OU=CMCC,OU=_CORP,DC=oneadr,DC=net</String>
              </List>
            </Value>
          </Filter>
          <Filter ignoreCase="true" operation="CONTAINS_ALL" property="memberOf">
            <Value>
              <List>
                <String>CN=sec-CMCC-CMA1TS0042 local admin,OU=CMCC Ser Local Adm,OU=Groups,OU=CMCC,OU=_CORP,DC=oneadr,DC=net</String>
              </List>
            </Value>
          </Filter>
          <Filter ignoreCase="true" operation="CONTAINS_ALL" property="memberOf">
            <Value>
              <List>
                <String>CN=sec-CMCC-CMA1TS0043 local admin,OU=CMCC Ser Local Adm,OU=Groups,OU=CMCC,OU=_CORP,DC=oneadr,DC=net</String>
              </List>
            </Value>
          </Filter>
          <Filter ignoreCase="true" operation="CONTAINS_ALL" property="memberOf">
            <Value>
              <List>
                <String>CN=sec-CMCC-CMA1TS0044 local admin,OU=CMCC Ser Local Adm,OU=Groups,OU=CMCC,OU=_CORP,DC=oneadr,DC=net</String>
              </List>
            </Value>
          </Filter>
          <Filter ignoreCase="true" operation="CONTAINS_ALL" property="memberOf">
            <Value>
              <List>
                <String>CN=sec-CMCC-CMA1TS0045 local admin,OU=CMCC Ser Local Adm,OU=Groups,OU=CMCC,OU=_CORP,DC=oneadr,DC=net</String>
              </List>
            </Value>
          </Filter>
          <Filter ignoreCase="true" operation="CONTAINS_ALL" property="memberOf">
            <Value>
              <List>
                <String>CN=sec-CMCC-CMA1TS0046 local admin,OU=CMCC Ser Local Adm,OU=Groups,OU=CMCC,OU=_CORP,DC=oneadr,DC=net</String>
              </List>
            </Value>
          </Filter>
          <Filter ignoreCase="true" operation="CONTAINS_ALL" property="memberOf">
            <Value>
              <List>
                <String>CN=sec-CMCC-CMA1TS0047 local admin,OU=CMCC Ser Local Adm,OU=Groups,OU=CMCC,OU=_CORP,DC=oneadr,DC=net</String>
              </List>
            </Value>
          </Filter>
          <Filter ignoreCase="true" operation="CONTAINS_ALL" property="memberOf">
            <Value>
              <List>
                <String>CN=sec-CMCC-CMA1TS0062 local admin,OU=CMCC Ser Local Adm,OU=Groups,OU=CMCC,OU=_CORP,DC=oneadr,DC=net</String>
              </List>
            </Value>
          </Filter>
          <Filter ignoreCase="true" operation="CONTAINS_ALL" property="memberOf">
            <Value>
              <List>
                <String>CN=sec-CMCC-CMA1CS0285 local admin,OU=CMCC Ser Local Adm,OU=Groups,OU=CMCC,OU=_CORP,DC=oneadr,DC=net</String>
              </List>
            </Value>
          </Filter>
          <Filter ignoreCase="true" operation="CONTAINS_ALL" property="memberOf">
            <Value>
              <List>
                <String>CN=sec-CMCC-CMA1CS0286 local admin,OU=CMCC Ser Local Adm,OU=Groups,OU=CMCC,OU=_CORP,DC=oneadr,DC=net</String>
              </List>
            </Value>
          </Filter>
          <Filter ignoreCase="true" operation="CONTAINS_ALL" property="memberOf">
            <Value>
              <List>
                <String>CN=sec-CMCC-CMA1CS0287 local admin,OU=CMCC Ser Local Adm,OU=Groups,OU=CMCC,OU=_CORP,DC=oneadr,DC=net</String>
              </List>
            </Value>
          </Filter>
          <Filter ignoreCase="true" operation="CONTAINS_ALL" property="memberOf">
            <Value>
              <List>
                <String>CN=sec-CMCC-CMA1CS0288 local admin,OU=CMCC Ser Local Adm,OU=Groups,OU=CMCC,OU=_CORP,DC=oneadr,DC=net</String>
              </List>
            </Value>
          </Filter>
          <Filter ignoreCase="true" operation="CONTAINS_ALL" property="memberOf">
            <Value>
              <List>
                <String>CN=sec-CMCC-CMA1CS0381 Local admin,OU=CMCC Ser Local Adm,OU=Groups,OU=CMCC,OU=_CORP,DC=oneadr,DC=net</String>
              </List>
            </Value>
          </Filter>
          <Filter ignoreCase="true" operation="CONTAINS_ALL" property="memberOf">
            <Value>
              <List>
                <String>CN=sec-CMCC-CMA1CS0382 Local admin,OU=CMCC Ser Local Adm,OU=Groups,OU=CMCC,OU=_CORP,DC=oneadr,DC=net</String>
              </List>
            </Value>
          </Filter>
          <Filter ignoreCase="true" operation="CONTAINS_ALL" property="memberOf">
            <Value>
              <List>
                <String>CN=sec-CMCC-CMA1CS0385 local admin,OU=CMCC Ser Local Adm,OU=Groups,OU=CMCC,OU=_CORP,DC=oneadr,DC=net</String>
              </List>
            </Value>
          </Filter>
          <Filter ignoreCase="true" operation="CONTAINS_ALL" property="memberOf">
            <Value>
              <List>
                <String>CN=sec-CMCC-CMA1CS0386 local admin,OU=CMCC Ser Local Adm,OU=Groups,OU=CMCC,OU=_CORP,DC=oneadr,DC=net</String>
              </List>
            </Value>
          </Filter>
          <Filter ignoreCase="true" operation="CONTAINS_ALL" property="memberOf">
            <Value>
              <List>
                <String>CN=sec-CMCC-CMA1CS0387 local admin,OU=CMCC Ser Local Adm,OU=Groups,OU=CMCC,OU=_CORP,DC=oneadr,DC=net</String>
              </List>
            </Value>
          </Filter>
          <Filter ignoreCase="true" operation="CONTAINS_ALL" property="memberOf">
            <Value>
              <List>
                <String>CN=sec-CMCC-CMA1CS0388 local admin,OU=CMCC Ser Local Adm,OU=Groups,OU=CMCC,OU=_CORP,DC=oneadr,DC=net</String>
              </List>
            </Value>
          </Filter>
          <Filter ignoreCase="true" operation="CONTAINS_ALL" property="memberOf">
            <Value>
              <List>
                <String>CN=sec-CMCC-CMA1CS0389 local admin,OU=CMCC Ser Local Adm,OU=Groups,OU=CMCC,OU=_CORP,DC=oneadr,DC=net</String>
              </List>
            </Value>
          </Filter>
          <Filter ignoreCase="true" operation="CONTAINS_ALL" property="memberOf">
            <Value>
              <List>
                <String>CN=sec-CMCC-CMA1CS0184 local admin,OU=CMCC Ser Local Adm,OU=Groups,OU=CMCC,OU=_CORP,DC=oneadr,DC=net</String>
              </List>
            </Value>
          </Filter>
          <Filter ignoreCase="true" operation="CONTAINS_ALL" property="memberOf">
            <Value>
              <List>
                <String>CN=sec-CMCC-CMA1CS0185 local admin,OU=CMCC Ser Local Adm,OU=Groups,OU=CMCC,OU=_CORP,DC=oneadr,DC=net</String>
              </List>
            </Value>
          </Filter>
          <Filter ignoreCase="true" operation="CONTAINS_ALL" property="memberOf">
            <Value>
              <List>
                <String>CN=sec-CMCC-CMA1TS0061 local admin,OU=CMCC Ser Local Adm,OU=Groups,OU=CMCC,OU=_CORP,DC=oneadr,DC=net</String>
              </List>
            </Value>
          </Filter>
          <Filter ignoreCase="true" operation="CONTAINS_ALL" property="memberOf">
            <Value>
              <List>
                <String>CN=sec-CMCC-CMA1GE0058 local admin,OU=CMCC Ser Local Adm,OU=Groups,OU=CMCC,OU=_CORP,DC=oneadr,DC=net</String>
              </List>
            </Value>
          </Filter>
          <Filter ignoreCase="true" operation="CONTAINS_ALL" property="memberOf">
            <Value>
              <List>
                <String>CN=sec-CMCC-CMA1GE0054 local admin,OU=CMCC Ser Local Adm,OU=Groups,OU=CMCC,OU=_CORP,DC=oneadr,DC=net</String>
              </List>
            </Value>
          </Filter>
          <Filter ignoreCase="true" operation="CONTAINS_ALL" property="memberOf">
            <Value>
              <List>
                <String>CN=sec-CMCC-CMA1GE0055 local admin,OU=CMCC Ser Local Adm,OU=Groups,OU=CMCC,OU=_CORP,DC=oneadr,DC=net</String>
              </List>
            </Value>
          </Filter>
          <Filter ignoreCase="true" operation="CONTAINS_ALL" property="memberOf">
            <Value>
              <List>
                <String>CN=sec-CMCC-CMA1GE0048 local admin,OU=CMCC Ser Local Adm,OU=Groups,OU=CMCC,OU=_CORP,DC=oneadr,DC=net</String>
              </List>
            </Value>
          </Filter>
          <Filter ignoreCase="true" operation="CONTAINS_ALL" property="memberOf">
            <Value>
              <List>
                <String>CN=sec-CMCC-CMA1GE0049 local admin,OU=CMCC Ser Local Adm,OU=Groups,OU=CMCC,OU=_CORP,DC=oneadr,DC=net</String>
              </List>
            </Value>
          </Filter>
          <Filter ignoreCase="true" operation="CONTAINS_ALL" property="memberOf">
            <Value>
              <List>
                <String>CN=sec-CMCC-CMA1CS0390 local admin,OU=CMCC Ser Local Adm,OU=Groups,OU=CMCC,OU=_CORP,DC=oneadr,DC=net</String>
              </List>
            </Value>
          </Filter>
          <Filter ignoreCase="true" operation="CONTAINS_ALL" property="memberOf">
            <Value>
              <List>
                <String>CN=sec-CMCC-CMA1CS0391 local admin,OU=CMCC Ser Local Adm,OU=Groups,OU=CMCC,OU=_CORP,DC=oneadr,DC=net</String>
              </List>
            </Value>
          </Filter>
          <Filter ignoreCase="true" operation="CONTAINS_ALL" property="memberOf">
            <Value>
              <List>
                <String>CN=sec-CMCC-CMA1CS0392 local admin,OU=CMCC Ser Local Adm,OU=Groups,OU=CMCC,OU=_CORP,DC=oneadr,DC=net</String>
              </List>
            </Value>
          </Filter>
          <Filter ignoreCase="true" operation="CONTAINS_ALL" property="memberOf">
            <Value>
              <List>
                <String>CN=sec-CMCC-CMA1CS0393 local admin,OU=CMCC Ser Local Adm,OU=Groups,OU=CMCC,OU=_CORP,DC=oneadr,DC=net</String>
              </List>
            </Value>
          </Filter>
          <Filter ignoreCase="true" operation="CONTAINS_ALL" property="memberOf">
            <Value>
              <List>
                <String>CN=sec-CMCC-CMA1CS0394 local admin,OU=CMCC Ser Local Adm,OU=Groups,OU=CMCC,OU=_CORP,DC=oneadr,DC=net</String>
              </List>
            </Value>
          </Filter>
          <Filter ignoreCase="true" operation="CONTAINS_ALL" property="memberOf">
            <Value>
              <List>
                <String>CN=sec-CMCC-CMA1CS0395 local admin,OU=CMCC Ser Local Adm,OU=Groups,OU=CMCC,OU=_CORP,DC=oneadr,DC=net</String>
              </List>
            </Value>
          </Filter>
          <Filter ignoreCase="true" operation="CONTAINS_ALL" property="memberOf">
            <Value>
              <List>
                <String>CN=sec-CMCC-CMA1CS0401 local admin,OU=CMCC Ser Local Adm,OU=Groups,OU=CMCC,OU=_CORP,DC=oneadr,DC=net</String>
              </List>
            </Value>
          </Filter>
          <Filter ignoreCase="true" operation="CONTAINS_ALL" property="memberOf">
            <Value>
              <List>
                <String>CN=sec-CMCC-DKA1TS0135 local admin,OU=CMCC Ser Local Adm,OU=Groups,OU=CMCC,OU=_CORP,DC=oneadr,DC=net</String>
              </List>
            </Value>
          </Filter>
          <Filter ignoreCase="true" operation="CONTAINS_ALL" property="memberOf">
            <Value>
              <List>
                <String>CN=SG CMA1CS0398 Local Admins,OU=CMCC Ser Local Adm,OU=Groups,OU=CMCC,OU=_CORP,DC=oneadr,DC=net</String>
              </List>
            </Value>
          </Filter>
          <Filter ignoreCase="true" operation="CONTAINS_ALL" property="memberOf">
            <Value>
              <List>
                <String>CN=SG CMA1CS0399 Local Admins,OU=CMCC Ser Local Adm,OU=Groups,OU=CMCC,OU=_CORP,DC=oneadr,DC=net</String>
              </List>
            </Value>
          </Filter>
          <Filter ignoreCase="true" operation="CONTAINS_ALL" property="memberOf">
            <Value>
              <List>
                <String>CN=sec-CMCC-CMA1CS0359 local admin,OU=CMCC Ser Local Adm,OU=Groups,OU=CMCC,OU=_CORP,DC=oneadr,DC=net</String>
              </List>
            </Value>
          </Filter>
          <Filter ignoreCase="true" operation="CONTAINS_ALL" property="memberOf">
            <Value>
              <List>
                <String>CN=sec-CMCC-CMA1CS0361 local admin,OU=CMCC Ser Local Adm,OU=Groups,OU=CMCC,OU=_CORP,DC=oneadr,DC=net</String>
              </List>
            </Value>
          </Filter>
          <Filter ignoreCase="true" operation="CONTAINS_ALL" property="memberOf">
            <Value>
              <List>
                <String>CN=sec-CMCC-CMA1CS0353 local admin,OU=CMCC Ser Local Adm,OU=Groups,OU=CMCC,OU=_CORP,DC=oneadr,DC=net</String>
              </List>
            </Value>
          </Filter>
          <Filter ignoreCase="true" operation="CONTAINS_ALL" property="memberOf">
            <Value>
              <List>
                <String>CN=sec-CMCC-CMA1CS0360 local admin,OU=CMCC Ser Local Adm,OU=Groups,OU=CMCC,OU=_CORP,DC=oneadr,DC=net</String>
              </List>
            </Value>
          </Filter>
          <Filter ignoreCase="true" operation="CONTAINS_ALL" property="memberOf">
            <Value>
              <List>
                <String>CN=sec-CMCC-CMA1CS0356 local admin,OU=CMCC Ser Local Adm,OU=Groups,OU=CMCC,OU=_CORP,DC=oneadr,DC=net</String>
              </List>
            </Value>
          </Filter>
          <Filter ignoreCase="true" operation="CONTAINS_ALL" property="memberOf">
            <Value>
              <List>
                <String>CN=sec-CMCC-CMA1CS0357 local admin,OU=CMCC Ser Local Adm,OU=Groups,OU=CMCC,OU=_CORP,DC=oneadr,DC=net</String>
              </List>
            </Value>
          </Filter>
          <Filter ignoreCase="true" operation="CONTAINS_ALL" property="memberOf">
            <Value>
              <List>
                <String>CN=sec-CMCC-CMA1CS0358 local admin,OU=CMCC Ser Local Adm,OU=Groups,OU=CMCC,OU=_CORP,DC=oneadr,DC=net</String>
              </List>
            </Value>
          </Filter>
          <Filter ignoreCase="true" operation="CONTAINS_ALL" property="memberOf">
            <Value>
              <List>
                <String>CN=sec-CMCC-CMA1CS0354 local admin,OU=CMCC Ser Local Adm,OU=Groups,OU=CMCC,OU=_CORP,DC=oneadr,DC=net</String>
              </List>
            </Value>
          </Filter>
          <Filter ignoreCase="true" operation="CONTAINS_ALL" property="memberOf">
            <Value>
              <List>
                <String>CN=sec-CMCC-CMA1CS0355 local admin,OU=CMCC Ser Local Adm,OU=Groups,OU=CMCC,OU=_CORP,DC=oneadr,DC=net</String>
              </List>
            </Value>
          </Filter>
          <Filter ignoreCase="true" operation="CONTAINS_ALL" property="memberOf">
            <Value>
              <List>
                <String>CN=sec-CMCC-CMA1CS0352 local admin,OU=CMCC Ser Local Adm,OU=Groups,OU=CMCC,OU=_CORP,DC=oneadr,DC=net</String>
              </List>
            </Value>
          </Filter>
          <Filter ignoreCase="true" operation="CONTAINS_ALL" property="memberOf">
            <Value>
              <List>
                <String>CN=sec-CMCC-CMA1GE0007 local admin,OU=CMCC Ser Local Adm,OU=Groups,OU=CMCC,OU=_CORP,DC=oneadr,DC=net</String>
              </List>
            </Value>
          </Filter>
          <Filter ignoreCase="true" operation="CONTAINS_ALL" property="memberOf">
            <Value>
              <List>
                <String>CN=sec-CMCC-CMA1CS0420 local admin,OU=DKD1,OU=Migrated Groups,OU=Groups,OU=CMCC,OU=_CORP,DC=oneadr,DC=net</String>
              </List>
            </Value>
          </Filter>
          <Filter ignoreCase="true" operation="CONTAINS_ALL" property="memberOf">
            <Value>
              <List>
                <String>CN=sec-CMCC-CMA1TS0070 Local Admins,OU=Til Sortering,OU=DKD1,OU=Migrated Groups,OU=Groups,OU=CMCC,OU=_CORP,DC=oneadr,DC=net</String>
              </List>
            </Value>
          </Filter>
          <Filter ignoreCase="true" operation="CONTAINS_ALL" property="memberOf">
            <Value>
              <List>
                <String>CN=sec-CMCC-CMA1TS0071 Local Admins,OU=DKD1,OU=Migrated Groups,OU=Groups,OU=CMCC,OU=_CORP,DC=oneadr,DC=net</String>
              </List>
            </Value>
          </Filter>
          <Filter ignoreCase="true" operation="CONTAINS_ALL" property="memberOf">
            <Value>
              <List>
                <String>CN=sec-CMCC-CMA1TS0075 Local Admins,OU=DKD1,OU=Migrated Groups,OU=Groups,OU=CMCC,OU=_CORP,DC=oneadr,DC=net</String>
              </List>
            </Value>
          </Filter>
          <Filter ignoreCase="true" operation="CONTAINS_ALL" property="memberOf">
            <Value>
              <List>
                <String>CN=sec-CMCC-CMA1TS0074 Local Admins,OU=DKD1,OU=Migrated Groups,OU=Groups,OU=CMCC,OU=_CORP,DC=oneadr,DC=net</String>
              </List>
            </Value>
          </Filter>
          <Filter ignoreCase="true" operation="CONTAINS_ALL" property="memberOf">
            <Value>
              <List>
                <String>CN=sec-CMCC-CMA1TS0073 Local Admins,OU=DKD1,OU=Migrated Groups,OU=Groups,OU=CMCC,OU=_CORP,DC=oneadr,DC=net</String>
              </List>
            </Value>
          </Filter>
          <Filter ignoreCase="true" operation="CONTAINS_ALL" property="memberOf">
            <Value>
              <List>
                <String>CN=sec-CMCC-CMA1TS0072 Local Admins,OU=DKD1,OU=Migrated Groups,OU=Groups,OU=CMCC,OU=_CORP,DC=oneadr,DC=net</String>
              </List>
            </Value>
          </Filter>
          <Filter ignoreCase="true" operation="CONTAINS_ALL" property="memberOf">
            <Value>
              <List>
                <String>CN=SG DKA1IS0002 Local Admins,OU=CMCC Ser Local Adm,OU=Groups,OU=CMCC,OU=_CORP,DC=oneadr,DC=net</String>
              </List>
            </Value>
          </Filter>
          <Filter ignoreCase="true" operation="CONTAINS_ALL" property="memberOf">
            <Value>
              <List>
                <String>CN=SG DKA1GE0054 Local Admins,OU=CMCC Ser Local Adm,OU=Groups,OU=CMCC,OU=_CORP,DC=oneadr,DC=net</String>
              </List>
            </Value>
          </Filter>
          <Filter ignoreCase="true" operation="CONTAINS_ALL" property="memberOf">
            <Value>
              <List>
                <String>CN=SG DKA1GE0049 Local Admins,OU=CMCC Ser Local Adm,OU=Groups,OU=CMCC,OU=_CORP,DC=oneadr,DC=net</String>
              </List>
            </Value>
          </Filter>
          <Filter ignoreCase="true" operation="CONTAINS_ALL" property="memberOf">
            <Value>
              <List>
                <String>CN=SG DKA1GE0050 Local Admins,OU=CMCC Ser Local Adm,OU=Groups,OU=CMCC,OU=_CORP,DC=oneadr,DC=net</String>
              </List>
            </Value>
          </Filter>
          <Filter ignoreCase="true" operation="CONTAINS_ALL" property="memberOf">
            <Value>
              <List>
                <String>CN=SG DKA1GE0055 Local Admins,OU=CMCC Ser Local Adm,OU=Groups,OU=CMCC,OU=_CORP,DC=oneadr,DC=net</String>
              </List>
            </Value>
          </Filter>
          <Filter ignoreCase="true" operation="CONTAINS_ALL" property="memberOf">
            <Value>
              <List>
                <String>CN=SG DKA1GE0057 Local Admins,OU=CMCC Ser Local Adm,OU=Groups,OU=CMCC,OU=_CORP,DC=oneadr,DC=net</String>
              </List>
            </Value>
          </Filter>
          <Filter ignoreCase="true" operation="CONTAINS_ALL" property="memberOf">
            <Value>
              <List>
                <String>CN=SG DKA1GE0053 Local Admins,OU=CMCC Ser Local Adm,OU=Groups,OU=CMCC,OU=_CORP,DC=oneadr,DC=net</String>
              </List>
            </Value>
          </Filter>
          <Filter ignoreCase="true" operation="CONTAINS_ALL" property="memberOf">
            <Value>
              <List>
                <String>CN=SG DKA1GE0056 Local Admins,OU=CMCC Ser Local Adm,OU=Groups,OU=CMCC,OU=_CORP,DC=oneadr,DC=net</String>
              </List>
            </Value>
          </Filter>
          <Filter ignoreCase="true" operation="CONTAINS_ALL" property="memberOf">
            <Value>
              <List>
                <String>CN=SG DKA1GE0048 Local Admins,OU=CMCC Ser Local Adm,OU=Groups,OU=CMCC,OU=_CORP,DC=oneadr,DC=net</String>
              </List>
            </Value>
          </Filter>
          <Filter ignoreCase="true" operation="CONTAINS_ALL" property="memberOf">
            <Value>
              <List>
                <String>CN=SG DKA1TS0028 Local Admins,OU=CMCC Ser Local Adm,OU=Groups,OU=CMCC,OU=_CORP,DC=oneadr,DC=net</String>
              </List>
            </Value>
          </Filter>
          <Filter ignoreCase="true" operation="CONTAINS_ALL" property="memberOf">
            <Value>
              <List>
                <String>CN=SG DKA1TS0024 Local Admins,OU=CMCC Ser Local Adm,OU=Groups,OU=CMCC,OU=_CORP,DC=oneadr,DC=net</String>
              </List>
            </Value>
          </Filter>
          <Filter ignoreCase="true" operation="CONTAINS_ALL" property="memberOf">
            <Value>
              <List>
                <String>CN=SG DKA1TS0009 Local Admins,OU=CMCC Ser Local Adm,OU=Groups,OU=CMCC,OU=_CORP,DC=oneadr,DC=net</String>
              </List>
            </Value>
          </Filter>
          <Filter ignoreCase="true" operation="CONTAINS_ALL" property="memberOf">
            <Value>
              <List>
                <String>CN=SG DKA1TS0140 Local Admins,OU=CMCC Ser Local Adm,OU=Groups,OU=CMCC,OU=_CORP,DC=oneadr,DC=net</String>
              </List>
            </Value>
          </Filter>
          <Filter ignoreCase="true" operation="CONTAINS_ALL" property="memberOf">
            <Value>
              <List>
                <String>CN=SG DKA1TS0010 Local Admins,OU=CMCC Ser Local Adm,OU=Groups,OU=CMCC,OU=_CORP,DC=oneadr,DC=net</String>
              </List>
            </Value>
          </Filter>
          <Filter ignoreCase="true" operation="CONTAINS_ALL" property="memberOf">
            <Value>
              <List>
                <String>CN=SG DKA1TS0013 Local Admins,OU=CMCC Ser Local Adm,OU=Groups,OU=CMCC,OU=_CORP,DC=oneadr,DC=net</String>
              </List>
            </Value>
          </Filter>
          <Filter ignoreCase="true" operation="CONTAINS_ALL" property="memberOf">
            <Value>
              <List>
                <String>CN=SG DKA1XS0019 Local Admins,OU=CMCC Ser Local Adm,OU=Groups,OU=CMCC,OU=_CORP,DC=oneadr,DC=net</String>
              </List>
            </Value>
          </Filter>
          <Filter ignoreCase="true" operation="CONTAINS_ALL" property="memberOf">
            <Value>
              <List>
                <String>CN=SG DKA1TS0022 Local Admins,OU=CMCC Ser Local Adm,OU=Groups,OU=CMCC,OU=_CORP,DC=oneadr,DC=net</String>
              </List>
            </Value>
          </Filter>
          <Filter ignoreCase="true" operation="CONTAINS_ALL" property="memberOf">
            <Value>
              <List>
                <String>CN=SG DKA1TS0008 Local Admins,OU=CMCC Ser Local Adm,OU=Groups,OU=CMCC,OU=_CORP,DC=oneadr,DC=net</String>
              </List>
            </Value>
          </Filter>
          <Filter ignoreCase="true" operation="CONTAINS_ALL" property="memberOf">
            <Value>
              <List>
                <String>CN=SG DKA1TS0023 Local Admins,OU=CMCC Ser Local Adm,OU=Groups,OU=CMCC,OU=_CORP,DC=oneadr,DC=net</String>
              </List>
            </Value>
          </Filter>
          <Filter ignoreCase="true" operation="CONTAINS_ALL" property="memberOf">
            <Value>
              <List>
                <String>CN=SG DKA1TS0150 Local Admins,OU=CMCC Ser Local Adm,OU=Groups,OU=CMCC,OU=_CORP,DC=oneadr,DC=net</String>
              </List>
            </Value>
          </Filter>
          <Filter ignoreCase="true" operation="CONTAINS_ALL" property="memberOf">
            <Value>
              <List>
                <String>CN=SG DKA1TS0135 Local Admins,OU=CMCC Ser Local Adm,OU=Groups,OU=CMCC,OU=_CORP,DC=oneadr,DC=net</String>
              </List>
            </Value>
          </Filter>
          <Filter ignoreCase="true" operation="CONTAINS_ALL" property="memberOf">
            <Value>
              <List>
                <String>CN=SG DKA1TS0012 Local Admins,OU=CMCC Ser Local Adm,OU=Groups,OU=CMCC,OU=_CORP,DC=oneadr,DC=net</String>
              </List>
            </Value>
          </Filter>
          <Filter ignoreCase="true" operation="CONTAINS_ALL" property="memberOf">
            <Value>
              <List>
                <String>CN=SG DKA1TS0136 Local Admins,OU=CMCC Ser Local Adm,OU=Groups,OU=CMCC,OU=_CORP,DC=oneadr,DC=net</String>
              </List>
            </Value>
          </Filter>
          <Filter ignoreCase="true" operation="CONTAINS_ALL" property="memberOf">
            <Value>
              <List>
                <String>CN=SG DKA1TS0027 Local Admins,OU=CMCC Ser Local Adm,OU=Groups,OU=CMCC,OU=_CORP,DC=oneadr,DC=net</String>
              </List>
            </Value>
          </Filter>
          <Filter ignoreCase="true" operation="CONTAINS_ALL" property="memberOf">
            <Value>
              <List>
                <String>CN=SG DKA1TS0011 Local Admins,OU=CMCC Ser Local Adm,OU=Groups,OU=CMCC,OU=_CORP,DC=oneadr,DC=net</String>
              </List>
            </Value>
          </Filter>
          <Filter ignoreCase="true" operation="CONTAINS_ALL" property="memberOf">
            <Value>
              <List>
                <String>CN=SG DKA1TS0007 Local Admins,OU=CMCC Ser Local Adm,OU=Groups,OU=CMCC,OU=_CORP,DC=oneadr,DC=net</String>
              </List>
            </Value>
          </Filter>
          <Filter ignoreCase="true" operation="CONTAINS_ALL" property="memberOf">
            <Value>
              <List>
                <String>CN=SG DKA1TS0149 Local Admins,OU=CMCC Ser Local Adm,OU=Groups,OU=CMCC,OU=_CORP,DC=oneadr,DC=net</String>
              </List>
            </Value>
          </Filter>
          <Filter ignoreCase="true" operation="CONTAINS_ALL" property="memberOf">
            <Value>
              <List>
                <String>CN=SG DKA1XS0011 Local Admins,OU=CMCC Ser Local Adm,OU=Groups,OU=CMCC,OU=_CORP,DC=oneadr,DC=net</String>
              </List>
            </Value>
          </Filter>
          <Filter ignoreCase="true" operation="CONTAINS_ALL" property="memberOf">
            <Value>
              <List>
                <String>CN=SG DKA1CS0116 Local Admins,OU=CMCC Ser Local Adm,OU=Groups,OU=CMCC,OU=_CORP,DC=oneadr,DC=net</String>
              </List>
            </Value>
          </Filter>
          <Filter ignoreCase="true" operation="CONTAINS_ALL" property="memberOf">
            <Value>
              <List>
                <String>CN=SG DKA1CS0097 Local Admins,OU=CMCC Ser Local Adm,OU=Groups,OU=CMCC,OU=_CORP,DC=oneadr,DC=net</String>
              </List>
            </Value>
          </Filter>
          <Filter ignoreCase="true" operation="CONTAINS_ALL" property="memberOf">
            <Value>
              <List>
                <String>CN=SG DKA1CS0111 Local Admins,OU=CMCC Ser Local Adm,OU=Groups,OU=CMCC,OU=_CORP,DC=oneadr,DC=net</String>
              </List>
            </Value>
          </Filter>
          <Filter ignoreCase="true" operation="CONTAINS_ALL" property="memberOf">
            <Value>
              <List>
                <String>CN=SG DKA1CS0096 Local Admins,OU=CMCC Ser Local Adm,OU=Groups,OU=CMCC,OU=_CORP,DC=oneadr,DC=net</String>
              </List>
            </Value>
          </Filter>
          <Filter ignoreCase="true" operation="CONTAINS_ALL" property="memberOf">
            <Value>
              <List>
                <String>CN=SG DKA1CS0078 Local Admins,OU=CMCC Ser Local Adm,OU=Groups,OU=CMCC,OU=_CORP,DC=oneadr,DC=net</String>
              </List>
            </Value>
          </Filter>
          <Filter ignoreCase="true" operation="CONTAINS_ALL" property="memberOf">
            <Value>
              <List>
                <String>CN=SG DKA1CS0113 Local Admins,OU=CMCC Ser Local Adm,OU=Groups,OU=CMCC,OU=_CORP,DC=oneadr,DC=net</String>
              </List>
            </Value>
          </Filter>
          <Filter ignoreCase="true" operation="CONTAINS_ALL" property="memberOf">
            <Value>
              <List>
                <String>CN=SG DKA1CD0003 Local Admins,OU=CMCC Ser Local Adm,OU=Groups,OU=CMCC,OU=_CORP,DC=oneadr,DC=net</String>
              </List>
            </Value>
          </Filter>
          <Filter ignoreCase="true" operation="CONTAINS_ALL" property="memberOf">
            <Value>
              <List>
                <String>CN=SG DKA1CS0098 Local Admins,OU=CMCC Ser Local Adm,OU=Groups,OU=CMCC,OU=_CORP,DC=oneadr,DC=net</String>
              </List>
            </Value>
          </Filter>
          <Filter ignoreCase="true" operation="CONTAINS_ALL" property="memberOf">
            <Value>
              <List>
                <String>CN=SG DKA1CS0122 Local Admins,OU=CMCC Ser Local Adm,OU=Groups,OU=CMCC,OU=_CORP,DC=oneadr,DC=net</String>
              </List>
            </Value>
          </Filter>
          <Filter ignoreCase="true" operation="CONTAINS_ALL" property="memberOf">
            <Value>
              <List>
                <String>CN=SG DKA1CD0002 Local Admins,OU=CMCC Ser Local Adm,OU=Groups,OU=CMCC,OU=_CORP,DC=oneadr,DC=net</String>
              </List>
            </Value>
          </Filter>
          <Filter ignoreCase="true" operation="CONTAINS_ALL" property="memberOf">
            <Value>
              <List>
                <String>CN=SG DKA1CS0125 Local Admins,OU=CMCC Ser Local Adm,OU=Groups,OU=CMCC,OU=_CORP,DC=oneadr,DC=net</String>
              </List>
            </Value>
          </Filter>
          <Filter ignoreCase="true" operation="CONTAINS_ALL" property="memberOf">
            <Value>
              <List>
                <String>CN=SG DKA1CS0150 Local Admins,OU=CMCC Ser Local Adm,OU=Groups,OU=CMCC,OU=_CORP,DC=oneadr,DC=net</String>
              </List>
            </Value>
          </Filter>
          <Filter ignoreCase="true" operation="CONTAINS_ALL" property="memberOf">
            <Value>
              <List>
                <String>CN=SG DKA1CS0130 Local Admins,OU=CMCC Ser Local Adm,OU=Groups,OU=CMCC,OU=_CORP,DC=oneadr,DC=net</String>
              </List>
            </Value>
          </Filter>
          <Filter ignoreCase="true" operation="CONTAINS_ALL" property="memberOf">
            <Value>
              <List>
                <String>CN=SG DKA1CS0138 Local Admins,OU=CMCC Ser Local Adm,OU=Groups,OU=CMCC,OU=_CORP,DC=oneadr,DC=net</String>
              </List>
            </Value>
          </Filter>
          <Filter ignoreCase="true" operation="CONTAINS_ALL" property="memberOf">
            <Value>
              <List>
                <String>CN=SG DKA1CS0145 Local Admins,OU=CMCC Ser Local Adm,OU=Groups,OU=CMCC,OU=_CORP,DC=oneadr,DC=net</String>
              </List>
            </Value>
          </Filter>
          <Filter ignoreCase="true" operation="CONTAINS_ALL" property="memberOf">
            <Value>
              <List>
                <String>CN=SG DKA1CS0177 Local Admins,OU=CMCC Ser Local Adm,OU=Groups,OU=CMCC,OU=_CORP,DC=oneadr,DC=net</String>
              </List>
            </Value>
          </Filter>
          <Filter ignoreCase="true" operation="CONTAINS_ALL" property="memberOf">
            <Value>
              <List>
                <String>CN=SG DKA1CS0155 Local Admins,OU=CMCC Ser Local Adm,OU=Groups,OU=CMCC,OU=_CORP,DC=oneadr,DC=net</String>
              </List>
            </Value>
          </Filter>
          <Filter ignoreCase="true" operation="CONTAINS_ALL" property="memberOf">
            <Value>
              <List>
                <String>CN=SG DKA1CS0126 Local Admins,OU=CMCC Ser Local Adm,OU=Groups,OU=CMCC,OU=_CORP,DC=oneadr,DC=net</String>
              </List>
            </Value>
          </Filter>
          <Filter ignoreCase="true" operation="CONTAINS_ALL" property="memberOf">
            <Value>
              <List>
                <String>CN=SG DKA1CS0164 Local Admins,OU=CMCC Ser Local Adm,OU=Groups,OU=CMCC,OU=_CORP,DC=oneadr,DC=net</String>
              </List>
            </Value>
          </Filter>
          <Filter ignoreCase="true" operation="CONTAINS_ALL" property="memberOf">
            <Value>
              <List>
                <String>CN=SG DKA1CS0137 Local Admins,OU=CMCC Ser Local Adm,OU=Groups,OU=CMCC,OU=_CORP,DC=oneadr,DC=net</String>
              </List>
            </Value>
          </Filter>
          <Filter ignoreCase="true" operation="CONTAINS_ALL" property="memberOf">
            <Value>
              <List>
                <String>CN=SG DKA1CS0149 Local Admins,OU=CMCC Ser Local Adm,OU=Groups,OU=CMCC,OU=_CORP,DC=oneadr,DC=net</String>
              </List>
            </Value>
          </Filter>
          <Filter ignoreCase="true" operation="CONTAINS_ALL" property="memberOf">
            <Value>
              <List>
                <String>CN=SG DKA1CS0158 Local Admins,OU=CMCC Ser Local Adm,OU=Groups,OU=CMCC,OU=_CORP,DC=oneadr,DC=net</String>
              </List>
            </Value>
          </Filter>
          <Filter ignoreCase="true" operation="CONTAINS_ALL" property="memberOf">
            <Value>
              <List>
                <String>CN=SG DKA1CS0178 Local admins,OU=CMCC Ser Local Adm,OU=Groups,OU=CMCC,OU=_CORP,DC=oneadr,DC=net</String>
              </List>
            </Value>
          </Filter>
          <Filter ignoreCase="true" operation="CONTAINS_ALL" property="memberOf">
            <Value>
              <List>
                <String>CN=SG DKA1CS0124 Local Admins,OU=CMCC Ser Local Adm,OU=Groups,OU=CMCC,OU=_CORP,DC=oneadr,DC=net</String>
              </List>
            </Value>
          </Filter>
          <Filter ignoreCase="true" operation="CONTAINS_ALL" property="memberOf">
            <Value>
              <List>
                <String>CN=SG DKA1CS0151 Local Admins,OU=CMCC Ser Local Adm,OU=Groups,OU=CMCC,OU=_CORP,DC=oneadr,DC=net</String>
              </List>
            </Value>
          </Filter>
          <Filter ignoreCase="true" operation="CONTAINS_ALL" property="memberOf">
            <Value>
              <List>
                <String>CN=SG DKA1CS0136 Local Admins,OU=CMCC Ser Local Adm,OU=Groups,OU=CMCC,OU=_CORP,DC=oneadr,DC=net</String>
              </List>
            </Value>
          </Filter>
          <Filter ignoreCase="true" operation="CONTAINS_ALL" property="memberOf">
            <Value>
              <List>
                <String>CN=SG DKA1CS0147 Local Admins,OU=CMCC Ser Local Adm,OU=Groups,OU=CMCC,OU=_CORP,DC=oneadr,DC=net</String>
              </List>
            </Value>
          </Filter>
          <Filter ignoreCase="true" operation="CONTAINS_ALL" property="memberOf">
            <Value>
              <List>
                <String>CN=SG DKA1CS0144 Local Admins,OU=CMCC Ser Local Adm,OU=Groups,OU=CMCC,OU=_CORP,DC=oneadr,DC=net</String>
              </List>
            </Value>
          </Filter>
          <Filter ignoreCase="true" operation="CONTAINS_ALL" property="memberOf">
            <Value>
              <List>
                <String>CN=SG DKA1CS0181 Local Admins,OU=CMCC Ser Local Adm,OU=Groups,OU=CMCC,OU=_CORP,DC=oneadr,DC=net</String>
              </List>
            </Value>
          </Filter>
          <Filter ignoreCase="true" operation="CONTAINS_ALL" property="memberOf">
            <Value>
              <List>
                <String>CN=SG DKA1CS0143 Local Admins,OU=CMCC Ser Local Adm,OU=Groups,OU=CMCC,OU=_CORP,DC=oneadr,DC=net</String>
              </List>
            </Value>
          </Filter>
          <Filter ignoreCase="true" operation="CONTAINS_ALL" property="memberOf">
            <Value>
              <List>
                <String>CN=SG DKA1CS0165 Local Admins,OU=CMCC Ser Local Adm,OU=Groups,OU=CMCC,OU=_CORP,DC=oneadr,DC=net</String>
              </List>
            </Value>
          </Filter>
          <Filter ignoreCase="true" operation="CONTAINS_ALL" property="memberOf">
            <Value>
              <List>
                <String>CN=SG DKA1CS0133 Local Admins,OU=CMCC Ser Local Adm,OU=Groups,OU=CMCC,OU=_CORP,DC=oneadr,DC=net</String>
              </List>
            </Value>
          </Filter>
          <Filter ignoreCase="true" operation="CONTAINS_ALL" property="memberOf">
            <Value>
              <List>
                <String>CN=SG DKA1CS0172 Local Admins,OU=CMCC Ser Local Adm,OU=Groups,OU=CMCC,OU=_CORP,DC=oneadr,DC=net</String>
              </List>
            </Value>
          </Filter>
          <Filter ignoreCase="true" operation="CONTAINS_ALL" property="memberOf">
            <Value>
              <List>
                <String>CN=SG DKA1CS0148 Local Admins,OU=CMCC Ser Local Adm,OU=Groups,OU=CMCC,OU=_CORP,DC=oneadr,DC=net</String>
              </List>
            </Value>
          </Filter>
          <Filter ignoreCase="true" operation="CONTAINS_ALL" property="memberOf">
            <Value>
              <List>
                <String>CN=SG DKA1CS0166 Local Admins,OU=CMCC Ser Local Adm,OU=Groups,OU=CMCC,OU=_CORP,DC=oneadr,DC=net</String>
              </List>
            </Value>
          </Filter>
          <Filter ignoreCase="true" operation="CONTAINS_ALL" property="memberOf">
            <Value>
              <List>
                <String>CN=SG DKA1CS0182 Local Admins,OU=CMCC Ser Local Adm,OU=Groups,OU=CMCC,OU=_CORP,DC=oneadr,DC=net</String>
              </List>
            </Value>
          </Filter>
          <Filter ignoreCase="true" operation="CONTAINS_ALL" property="memberOf">
            <Value>
              <List>
                <String>CN=SG DKA1GE0047 Local Admins,OU=CMCC Ser Local Adm,OU=Groups,OU=CMCC,OU=_CORP,DC=oneadr,DC=net</String>
              </List>
            </Value>
          </Filter>
          <Filter ignoreCase="true" operation="CONTAINS_ALL" property="memberOf">
            <Value>
              <List>
                <String>CN=SG DKA1GE0046 Local Admins,OU=CMCC Ser Local Adm,OU=Groups,OU=CMCC,OU=_CORP,DC=oneadr,DC=net</String>
              </List>
            </Value>
          </Filter>
          <Filter ignoreCase="true" operation="CONTAINS_ALL" property="memberOf">
            <Value>
              <List>
                <String>CN=SG DKA1GE0045 Local Admins,OU=CMCC Ser Local Adm,OU=Groups,OU=CMCC,OU=_CORP,DC=oneadr,DC=net</String>
              </List>
            </Value>
          </Filter>
          <Filter ignoreCase="true" operation="CONTAINS_ALL" property="memberOf">
            <Value>
              <List>
                <String>CN=SG DKA1GE0032 Local Admins,OU=CMCC Ser Local Adm,OU=Groups,OU=CMCC,OU=_CORP,DC=oneadr,DC=net</String>
              </List>
            </Value>
          </Filter>
          <Filter ignoreCase="true" operation="CONTAINS_ALL" property="memberOf">
            <Value>
              <List>
                <String>CN=SG DKA1CS0208 Local Admins,OU=CMCC Ser Local Adm,OU=Groups,OU=CMCC,OU=_CORP,DC=oneadr,DC=net</String>
              </List>
            </Value>
          </Filter>
          <Filter ignoreCase="true" operation="CONTAINS_ALL" property="memberOf">
            <Value>
              <List>
                <String>CN=SG DKA1CS0207 Local Admins,OU=CMCC Ser Local Adm,OU=Groups,OU=CMCC,OU=_CORP,DC=oneadr,DC=net</String>
              </List>
            </Value>
          </Filter>
          <Filter ignoreCase="true" operation="CONTAINS_ALL" property="memberOf">
            <Value>
              <List>
                <String>CN=SG DKA1CS0199 Local Admins,OU=CMCC Ser Local Adm,OU=Groups,OU=CMCC,OU=_CORP,DC=oneadr,DC=net</String>
              </List>
            </Value>
          </Filter>
          <Filter ignoreCase="true" operation="CONTAINS_ALL" property="memberOf">
            <Value>
              <List>
                <String>CN=SG DKA1CS0198 Local Admins,OU=CMCC Ser Local Adm,OU=Groups,OU=CMCC,OU=_CORP,DC=oneadr,DC=net</String>
              </List>
            </Value>
          </Filter>
          <Filter ignoreCase="true" operation="CONTAINS_ALL" property="memberOf">
            <Value>
              <List>
                <String>CN=SG DKA1CS0197 Local Admins,OU=CMCC Ser Local Adm,OU=Groups,OU=CMCC,OU=_CORP,DC=oneadr,DC=net</String>
              </List>
            </Value>
          </Filter>
          <Filter ignoreCase="true" operation="CONTAINS_ALL" property="memberOf">
            <Value>
              <List>
                <String>CN=SG DKA1CS0192 Local admins,OU=CMCC Ser Local Adm,OU=Groups,OU=CMCC,OU=_CORP,DC=oneadr,DC=net</String>
              </List>
            </Value>
          </Filter>
          <Filter ignoreCase="true" operation="CONTAINS_ALL" property="memberOf">
            <Value>
              <List>
                <String>CN=SG DKA1CS0189 Local Admins,OU=CMCC Ser Local Adm,OU=Groups,OU=CMCC,OU=_CORP,DC=oneadr,DC=net</String>
              </List>
            </Value>
          </Filter>
          <Filter ignoreCase="true" operation="CONTAINS_ALL" property="memberOf">
            <Value>
              <List>
                <String>CN=SG DKA1CS0188 Local Admins,OU=CMCC Ser Local Adm,OU=Groups,OU=CMCC,OU=_CORP,DC=oneadr,DC=net</String>
              </List>
            </Value>
          </Filter>
          <Filter ignoreCase="true" operation="CONTAINS_ALL" property="memberOf">
            <Value>
              <List>
                <String>CN=SG DKA1CS0187 Local Admins,OU=CMCC Ser Local Adm,OU=Groups,OU=CMCC,OU=_CORP,DC=oneadr,DC=net</String>
              </List>
            </Value>
          </Filter>
          <Filter ignoreCase="true" operation="CONTAINS_ALL" property="memberOf">
            <Value>
              <List>
                <String>CN=SG DKA1CS0186 Local Admins,OU=CMCC Ser Local Adm,OU=Groups,OU=CMCC,OU=_CORP,DC=oneadr,DC=net</String>
              </List>
            </Value>
          </Filter>
          <Filter ignoreCase="true" operation="CONTAINS_ALL" property="memberOf">
            <Value>
              <List>
                <String>CN=SG DKA1CS0185 Local Admins,OU=CMCC Ser Local Adm,OU=Groups,OU=CMCC,OU=_CORP,DC=oneadr,DC=net</String>
              </List>
            </Value>
          </Filter>
          <Filter ignoreCase="true" operation="CONTAINS_ALL" property="memberOf">
            <Value>
              <List>
                <String>CN=SG DKA1CS0184 Local Admins,OU=CMCC Ser Local Adm,OU=Groups,OU=CMCC,OU=_CORP,DC=oneadr,DC=net</String>
              </List>
            </Value>
          </Filter>
          <Filter ignoreCase="true" operation="CONTAINS_ALL" property="memberOf">
            <Value>
              <List>
                <String>CN=SG DKA1CS0183 Local Admins,OU=CMCC Ser Local Adm,OU=Groups,OU=CMCC,OU=_CORP,DC=oneadr,DC=net</String>
              </List>
            </Value>
          </Filter>
          <Filter ignoreCase="true" operation="CONTAINS_ALL" property="memberOf">
            <Value>
              <List>
                <String>CN=SG CMA1CS0220 Local Admins,OU=CMCC Ser Local Adm,OU=Groups,OU=CMCC,OU=_CORP,DC=oneadr,DC=net</String>
              </List>
            </Value>
          </Filter>
          <Filter ignoreCase="true" operation="CONTAINS_ALL" property="memberOf">
            <Value>
              <List>
                <String>CN=SG CMA1CS0232 Local Admins,OU=CMCC Ser Local Adm,OU=Groups,OU=CMCC,OU=_CORP,DC=oneadr,DC=net</String>
              </List>
            </Value>
          </Filter>
          <Filter ignoreCase="true" operation="CONTAINS_ALL" property="memberOf">
            <Value>
              <List>
                <String>CN=SG CMA1CS0230 Local Admins,OU=CMCC Ser Local Adm,OU=Groups,OU=CMCC,OU=_CORP,DC=oneadr,DC=net</String>
              </List>
            </Value>
          </Filter>
          <Filter ignoreCase="true" operation="CONTAINS_ALL" property="memberOf">
            <Value>
              <List>
                <String>CN=SG CMA1CS0251 Local Admins,OU=CMCC Ser Local Adm,OU=Groups,OU=CMCC,OU=_CORP,DC=oneadr,DC=net</String>
              </List>
            </Value>
          </Filter>
          <Filter ignoreCase="true" operation="CONTAINS_ALL" property="memberOf">
            <Value>
              <List>
                <String>CN=SG CMA1CS0252 Local Admins,OU=CMCC Ser Local Adm,OU=Groups,OU=CMCC,OU=_CORP,DC=oneadr,DC=net</String>
              </List>
            </Value>
          </Filter>
          <Filter ignoreCase="true" operation="CONTAINS_ALL" property="memberOf">
            <Value>
              <List>
                <String>CN=SG CMA1CS0229 Local Admins,OU=CMCC Ser Local Adm,OU=Groups,OU=CMCC,OU=_CORP,DC=oneadr,DC=net</String>
              </List>
            </Value>
          </Filter>
          <Filter ignoreCase="true" operation="CONTAINS_ALL" property="memberOf">
            <Value>
              <List>
                <String>CN=SG CMA1CS0254 Local Admins,OU=CMCC Ser Local Adm,OU=Groups,OU=CMCC,OU=_CORP,DC=oneadr,DC=net</String>
              </List>
            </Value>
          </Filter>
          <Filter ignoreCase="true" operation="CONTAINS_ALL" property="memberOf">
            <Value>
              <List>
                <String>CN=SG CMA1CS0248 Local Admins,OU=CMCC Ser Local Adm,OU=Groups,OU=CMCC,OU=_CORP,DC=oneadr,DC=net</String>
              </List>
            </Value>
          </Filter>
          <Filter ignoreCase="true" operation="CONTAINS_ALL" property="memberOf">
            <Value>
              <List>
                <String>CN=SG CMA1CS0231 Local Admins,OU=CMCC Ser Local Adm,OU=Groups,OU=CMCC,OU=_CORP,DC=oneadr,DC=net</String>
              </List>
            </Value>
          </Filter>
          <Filter ignoreCase="true" operation="CONTAINS_ALL" property="memberOf">
            <Value>
              <List>
                <String>CN=SG CMA1CS0256 Local Admins,OU=CMCC Ser Local Adm,OU=Groups,OU=CMCC,OU=_CORP,DC=oneadr,DC=net</String>
              </List>
            </Value>
          </Filter>
          <Filter ignoreCase="true" operation="CONTAINS_ALL" property="memberOf">
            <Value>
              <List>
                <String>CN=SG CMA1CS0221 Local Admins,OU=CMCC Ser Local Adm,OU=Groups,OU=CMCC,OU=_CORP,DC=oneadr,DC=net</String>
              </List>
            </Value>
          </Filter>
          <Filter ignoreCase="true" operation="CONTAINS_ALL" property="memberOf">
            <Value>
              <List>
                <String>CN=SG CMA1CS0249 Local Admins,OU=CMCC Ser Local Adm,OU=Groups,OU=CMCC,OU=_CORP,DC=oneadr,DC=net</String>
              </List>
            </Value>
          </Filter>
          <Filter ignoreCase="true" operation="CONTAINS_ALL" property="memberOf">
            <Value>
              <List>
                <String>CN=SG CMA1CS0258 Local Admins,OU=CMCC Ser Local Adm,OU=Groups,OU=CMCC,OU=_CORP,DC=oneadr,DC=net</String>
              </List>
            </Value>
          </Filter>
          <Filter ignoreCase="true" operation="CONTAINS_ALL" property="memberOf">
            <Value>
              <List>
                <String>CN=SG CMA1CS0223 Local Admins,OU=CMCC Ser Local Adm,OU=Groups,OU=CMCC,OU=_CORP,DC=oneadr,DC=net</String>
              </List>
            </Value>
          </Filter>
          <Filter ignoreCase="true" operation="CONTAINS_ALL" property="memberOf">
            <Value>
              <List>
                <String>CN=SG CMA1CS0233 Local Admins,OU=CMCC Ser Local Adm,OU=Groups,OU=CMCC,OU=_CORP,DC=oneadr,DC=net</String>
              </List>
            </Value>
          </Filter>
          <Filter ignoreCase="true" operation="CONTAINS_ALL" property="memberOf">
            <Value>
              <List>
                <String>CN=SG CMA1CS0222 Local Admins,OU=CMCC Ser Local Adm,OU=Groups,OU=CMCC,OU=_CORP,DC=oneadr,DC=net</String>
              </List>
            </Value>
          </Filter>
          <Filter ignoreCase="true" operation="CONTAINS_ALL" property="memberOf">
            <Value>
              <List>
                <String>CN=SG CMA1CS0247 Local Admins,OU=CMCC Ser Local Adm,OU=Groups,OU=CMCC,OU=_CORP,DC=oneadr,DC=net</String>
              </List>
            </Value>
          </Filter>
          <Filter ignoreCase="true" operation="CONTAINS_ALL" property="memberOf">
            <Value>
              <List>
                <String>CN=SG CMA1CS0246 Local Admins,OU=CMCC Ser Local Adm,OU=Groups,OU=CMCC,OU=_CORP,DC=oneadr,DC=net</String>
              </List>
            </Value>
          </Filter>
          <Filter ignoreCase="true" operation="CONTAINS_ALL" property="memberOf">
            <Value>
              <List>
                <String>CN=SG CMA1CS0226 Local Admins,OU=CMCC Ser Local Adm,OU=Groups,OU=CMCC,OU=_CORP,DC=oneadr,DC=net</String>
              </List>
            </Value>
          </Filter>
          <Filter ignoreCase="true" operation="CONTAINS_ALL" property="memberOf">
            <Value>
              <List>
                <String>CN=SG CMA1CS0250 Local Admins,OU=CMCC Ser Local Adm,OU=Groups,OU=CMCC,OU=_CORP,DC=oneadr,DC=net</String>
              </List>
            </Value>
          </Filter>
          <Filter ignoreCase="true" operation="CONTAINS_ALL" property="memberOf">
            <Value>
              <List>
                <String>CN=SG CMA1CS0238 Local Admins,OU=CMCC Ser Local Adm,OU=Groups,OU=CMCC,OU=_CORP,DC=oneadr,DC=net</String>
              </List>
            </Value>
          </Filter>
          <Filter ignoreCase="true" operation="CONTAINS_ALL" property="memberOf">
            <Value>
              <List>
                <String>CN=SG CMA1CS0224 Local Admins,OU=CMCC Ser Local Adm,OU=Groups,OU=CMCC,OU=_CORP,DC=oneadr,DC=net</String>
              </List>
            </Value>
          </Filter>
          <Filter ignoreCase="true" operation="CONTAINS_ALL" property="memberOf">
            <Value>
              <List>
                <String>CN=SG CMA1CS0255 Local Admins,OU=CMCC Ser Local Adm,OU=Groups,OU=CMCC,OU=_CORP,DC=oneadr,DC=net</String>
              </List>
            </Value>
          </Filter>
          <Filter ignoreCase="true" operation="CONTAINS_ALL" property="memberOf">
            <Value>
              <List>
                <String>CN=SG CMA1CS0259 Local Admins,OU=CMCC Ser Local Adm,OU=Groups,OU=CMCC,OU=_CORP,DC=oneadr,DC=net</String>
              </List>
            </Value>
          </Filter>
          <Filter ignoreCase="true" operation="CONTAINS_ALL" property="memberOf">
            <Value>
              <List>
                <String>CN=SG CMA1CS0234 Local Admins,OU=CMCC Ser Local Adm,OU=Groups,OU=CMCC,OU=_CORP,DC=oneadr,DC=net</String>
              </List>
            </Value>
          </Filter>
          <Filter ignoreCase="true" operation="CONTAINS_ALL" property="memberOf">
            <Value>
              <List>
                <String>CN=SG CMA1CS0235 Local Admins,OU=CMCC Ser Local Adm,OU=Groups,OU=CMCC,OU=_CORP,DC=oneadr,DC=net</String>
              </List>
            </Value>
          </Filter>
          <Filter ignoreCase="true" operation="CONTAINS_ALL" property="memberOf">
            <Value>
              <List>
                <String>CN=SG CMA1CS0257 Local Admins,OU=CMCC Ser Local Adm,OU=Groups,OU=CMCC,OU=_CORP,DC=oneadr,DC=net</String>
              </List>
            </Value>
          </Filter>
          <Filter ignoreCase="true" operation="CONTAINS_ALL" property="memberOf">
            <Value>
              <List>
                <String>CN=SG CMA1CS0228 Local Admins,OU=CMCC Ser Local Adm,OU=Groups,OU=CMCC,OU=_CORP,DC=oneadr,DC=net</String>
              </List>
            </Value>
          </Filter>
          <Filter ignoreCase="true" operation="CONTAINS_ALL" property="memberOf">
            <Value>
              <List>
                <String>CN=SG CMA1CS0290 Local Admins,OU=CMCC Ser Local Adm,OU=Groups,OU=CMCC,OU=_CORP,DC=oneadr,DC=net</String>
              </List>
            </Value>
          </Filter>
          <Filter ignoreCase="true" operation="CONTAINS_ALL" property="memberOf">
            <Value>
              <List>
                <String>CN=SG CMA1CS0291 Local Admin,OU=CMCC Ser Local Adm,OU=Groups,OU=CMCC,OU=_CORP,DC=oneadr,DC=net</String>
              </List>
            </Value>
          </Filter>
          <Filter ignoreCase="true" operation="CONTAINS_ALL" property="memberOf">
            <Value>
              <List>
                <String>CN=SG CMA1TS0086 Local Admins,OU=CMCC Ser Local Adm,OU=Groups,OU=CMCC,OU=_CORP,DC=oneadr,DC=net</String>
              </List>
            </Value>
          </Filter>
          <Filter ignoreCase="true" operation="CONTAINS_ALL" property="memberOf">
            <Value>
              <List>
                <String>CN=SG CMA1TS0049 Local Admins,OU=CMCC Ser Local Adm,OU=Groups,OU=CMCC,OU=_CORP,DC=oneadr,DC=net</String>
              </List>
            </Value>
          </Filter>
          <Filter ignoreCase="true" operation="CONTAINS_ALL" property="memberOf">
            <Value>
              <List>
                <String>CN=SG CMA1GE0028 Local Admins,OU=CMCC Ser Local Adm,OU=Groups,OU=CMCC,OU=_CORP,DC=oneadr,DC=net</String>
              </List>
            </Value>
          </Filter>
          <Filter ignoreCase="true" operation="CONTAINS_ALL" property="memberOf">
            <Value>
              <List>
                <String>CN=SG CMA1CS0271 Local Admins,OU=CMCC Ser Local Adm,OU=Groups,OU=CMCC,OU=_CORP,DC=oneadr,DC=net</String>
              </List>
            </Value>
          </Filter>
          <Filter ignoreCase="true" operation="CONTAINS_ALL" property="memberOf">
            <Value>
              <List>
                <String>CN=SG CMA1TS0048 Local Admins,OU=CMCC Ser Local Adm,OU=Groups,OU=CMCC,OU=_CORP,DC=oneadr,DC=net</String>
              </List>
            </Value>
          </Filter>
          <Filter ignoreCase="true" operation="CONTAINS_ALL" property="memberOf">
            <Value>
              <List>
                <String>CN=SG CMA1CS0317 Local Admins,OU=CMCC Ser Local Adm,OU=Groups,OU=CMCC,OU=_CORP,DC=oneadr,DC=net</String>
              </List>
            </Value>
          </Filter>
          <Filter ignoreCase="true" operation="CONTAINS_ALL" property="memberOf">
            <Value>
              <List>
                <String>CN=SG CMA1GE0045 Local Admins,OU=CMCC Ser Local Adm,OU=Groups,OU=CMCC,OU=_CORP,DC=oneadr,DC=net</String>
              </List>
            </Value>
          </Filter>
          <Filter ignoreCase="true" operation="CONTAINS_ALL" property="memberOf">
            <Value>
              <List>
                <String>CN=SG CMA1TS0035 Local Admins,OU=CMCC Ser Local Adm,OU=Groups,OU=CMCC,OU=_CORP,DC=oneadr,DC=net</String>
              </List>
            </Value>
          </Filter>
          <Filter ignoreCase="true" operation="CONTAINS_ALL" property="memberOf">
            <Value>
              <List>
                <String>CN=SG CMA1TS0033 Local Admins,OU=CMCC Ser Local Adm,OU=Groups,OU=CMCC,OU=_CORP,DC=oneadr,DC=net</String>
              </List>
            </Value>
          </Filter>
          <Filter ignoreCase="true" operation="CONTAINS_ALL" property="memberOf">
            <Value>
              <List>
                <String>CN=SG CMA1CS0267 Local Admins,OU=CMCC Ser Local Adm,OU=Groups,OU=CMCC,OU=_CORP,DC=oneadr,DC=net</String>
              </List>
            </Value>
          </Filter>
          <Filter ignoreCase="true" operation="CONTAINS_ALL" property="memberOf">
            <Value>
              <List>
                <String>CN=SG CMA1TS0034 Local Admins,OU=CMCC Ser Local Adm,OU=Groups,OU=CMCC,OU=_CORP,DC=oneadr,DC=net</String>
              </List>
            </Value>
          </Filter>
          <Filter ignoreCase="true" operation="CONTAINS_ALL" property="memberOf">
            <Value>
              <List>
                <String>CN=SG CMA1CS0270 Local Admins,OU=CMCC Ser Local Adm,OU=Groups,OU=CMCC,OU=_CORP,DC=oneadr,DC=net</String>
              </List>
            </Value>
          </Filter>
          <Filter ignoreCase="true" operation="CONTAINS_ALL" property="memberOf">
            <Value>
              <List>
                <String>CN=SG CMA1CS0284 Local Admins,OU=CMCC Ser Local Adm,OU=Groups,OU=CMCC,OU=_CORP,DC=oneadr,DC=net</String>
              </List>
            </Value>
          </Filter>
          <Filter ignoreCase="true" operation="CONTAINS_ALL" property="memberOf">
            <Value>
              <List>
                <String>CN=SG CMA1GE0047 Local Admins,OU=CMCC Ser Local Adm,OU=Groups,OU=CMCC,OU=_CORP,DC=oneadr,DC=net</String>
              </List>
            </Value>
          </Filter>
          <Filter ignoreCase="true" operation="CONTAINS_ALL" property="memberOf">
            <Value>
              <List>
                <String>CN=SG CMA1TS0036 Local Admins,OU=CMCC Ser Local Adm,OU=Groups,OU=CMCC,OU=_CORP,DC=oneadr,DC=net</String>
              </List>
            </Value>
          </Filter>
          <Filter ignoreCase="true" operation="CONTAINS_ALL" property="memberOf">
            <Value>
              <List>
                <String>CN=SG CMA1TS0050 Local Admins,OU=CMCC Ser Local Adm,OU=Groups,OU=CMCC,OU=_CORP,DC=oneadr,DC=net</String>
              </List>
            </Value>
          </Filter>
          <Filter ignoreCase="true" operation="CONTAINS_ALL" property="memberOf">
            <Value>
              <List>
                <String>CN=SG CMA1GE0053 Local Admins,OU=CMCC Ser Local Adm,OU=Groups,OU=CMCC,OU=_CORP,DC=oneadr,DC=net</String>
              </List>
            </Value>
          </Filter>
          <Filter ignoreCase="true" operation="CONTAINS_ALL" property="memberOf">
            <Value>
              <List>
                <String>CN=SG CMA1CS0269 Local Admins,OU=CMCC Ser Local Adm,OU=Groups,OU=CMCC,OU=_CORP,DC=oneadr,DC=net</String>
              </List>
            </Value>
          </Filter>
          <Filter ignoreCase="true" operation="CONTAINS_ALL" property="memberOf">
            <Value>
              <List>
                <String>CN=SG CMA1TS0087 Local Admins,OU=CMCC Ser Local Adm,OU=Groups,OU=CMCC,OU=_CORP,DC=oneadr,DC=net</String>
              </List>
            </Value>
          </Filter>
          <Filter ignoreCase="true" operation="CONTAINS_ALL" property="memberOf">
            <Value>
              <List>
                <String>CN=SG CMA1CS0292 Local Admins,OU=CMCC Ser Local Adm,OU=Groups,OU=CMCC,OU=_CORP,DC=oneadr,DC=net</String>
              </List>
            </Value>
          </Filter>
          <Filter ignoreCase="true" operation="CONTAINS_ALL" property="memberOf">
            <Value>
              <List>
                <String>CN=SG CMA1CS0272 Local Admins,OU=CMCC Ser Local Adm,OU=Groups,OU=CMCC,OU=_CORP,DC=oneadr,DC=net</String>
              </List>
            </Value>
          </Filter>
          <Filter ignoreCase="true" operation="CONTAINS_ALL" property="memberOf">
            <Value>
              <List>
                <String>CN=SG CMA1CS0268 Local Admins,OU=CMCC Ser Local Adm,OU=Groups,OU=CMCC,OU=_CORP,DC=oneadr,DC=net</String>
              </List>
            </Value>
          </Filter>
          <Filter ignoreCase="true" operation="CONTAINS_ALL" property="memberOf">
            <Value>
              <List>
                <String>CN=SG CMA1GE0009 Local Admins,OU=CMCC Ser Local Adm,OU=Groups,OU=CMCC,OU=_CORP,DC=oneadr,DC=net</String>
              </List>
            </Value>
          </Filter>
          <Filter ignoreCase="true" operation="CONTAINS_ALL" property="memberOf">
            <Value>
              <List>
                <String>CN=SG CMA1TS0031 Local Admins,OU=CMCC Ser Local Adm,OU=Groups,OU=CMCC,OU=_CORP,DC=oneadr,DC=net</String>
              </List>
            </Value>
          </Filter>
          <Filter ignoreCase="true" operation="CONTAINS_ALL" property="memberOf">
            <Value>
              <List>
                <String>CN=SG CMA1TS0051 Local Admins,OU=CMCC Ser Local Adm,OU=Groups,OU=CMCC,OU=_CORP,DC=oneadr,DC=net</String>
              </List>
            </Value>
          </Filter>
          <Filter ignoreCase="true" operation="CONTAINS_ALL" property="memberOf">
            <Value>
              <List>
                <String>CN=SG CMA1TS0011 Local Admins,OU=CMCC Ser Local Adm,OU=Groups,OU=CMCC,OU=_CORP,DC=oneadr,DC=net</String>
              </List>
            </Value>
          </Filter>
          <Filter ignoreCase="true" operation="CONTAINS_ALL" property="memberOf">
            <Value>
              <List>
                <String>CN=SG CMA1TS0037 Local Admins,OU=CMCC Ser Local Adm,OU=Groups,OU=CMCC,OU=_CORP,DC=oneadr,DC=net</String>
              </List>
            </Value>
          </Filter>
          <Filter ignoreCase="true" operation="CONTAINS_ALL" property="memberOf">
            <Value>
              <List>
                <String>CN=SG CMA1TS0092 Local Admins,OU=CMCC Ser Local Adm,OU=Groups,OU=CMCC,OU=_CORP,DC=oneadr,DC=net</String>
              </List>
            </Value>
          </Filter>
          <Filter ignoreCase="true" operation="CONTAINS_ALL" property="memberOf">
            <Value>
              <List>
                <String>CN=SG CMA1TS0088 Local Admins,OU=CMCC Ser Local Adm,OU=Groups,OU=CMCC,OU=_CORP,DC=oneadr,DC=net</String>
              </List>
            </Value>
          </Filter>
          <Filter ignoreCase="true" operation="CONTAINS_ALL" property="memberOf">
            <Value>
              <List>
                <String>CN=SG CMA1CS0019 Local Admins,OU=CMCC Ser Local Adm,OU=Groups,OU=CMCC,OU=_CORP,DC=oneadr,DC=net</String>
              </List>
            </Value>
          </Filter>
          <Filter ignoreCase="true" operation="CONTAINS_ALL" property="memberOf">
            <Value>
              <List>
                <String>CN=SG CMA1CS0007 Local admins,OU=CMCC Ser Local Adm,OU=Groups,OU=CMCC,OU=_CORP,DC=oneadr,DC=net</String>
              </List>
            </Value>
          </Filter>
          <Filter ignoreCase="true" operation="CONTAINS_ALL" property="memberOf">
            <Value>
              <List>
                <String>CN=SG CMA1CS0001 Local Admins,OU=CMCC Ser Local Adm,OU=Groups,OU=CMCC,OU=_CORP,DC=oneadr,DC=net</String>
              </List>
            </Value>
          </Filter>
          <Filter ignoreCase="true" operation="CONTAINS_ALL" property="memberOf">
            <Value>
              <List>
                <String>CN=SG CMA1CS0002 Local Admin,OU=CMCC Ser Local Adm,OU=Groups,OU=CMCC,OU=_CORP,DC=oneadr,DC=net</String>
              </List>
            </Value>
          </Filter>
          <Filter ignoreCase="true" operation="CONTAINS_ALL" property="memberOf">
            <Value>
              <List>
                <String>CN=SG CMA1CS0015 Local Admins,OU=CMCC Ser Local Adm,OU=Groups,OU=CMCC,OU=_CORP,DC=oneadr,DC=net</String>
              </List>
            </Value>
          </Filter>
          <Filter ignoreCase="true" operation="CONTAINS_ALL" property="memberOf">
            <Value>
              <List>
                <String>CN=SG CMA1CS0005 Local Admins,OU=CMCC Ser Local Adm,OU=Groups,OU=CMCC,OU=_CORP,DC=oneadr,DC=net</String>
              </List>
            </Value>
          </Filter>
          <Filter ignoreCase="true" operation="CONTAINS_ALL" property="memberOf">
            <Value>
              <List>
                <String>CN=SG CMA1CS0003 Local Admins,OU=CMCC Ser Local Adm,OU=Groups,OU=CMCC,OU=_CORP,DC=oneadr,DC=net</String>
              </List>
            </Value>
          </Filter>
          <Filter ignoreCase="true" operation="CONTAINS_ALL" property="memberOf">
            <Value>
              <List>
                <String>CN=SG CMA1CS0039 Local Admins,OU=CMCC Ser Local Adm,OU=Groups,OU=CMCC,OU=_CORP,DC=oneadr,DC=net</String>
              </List>
            </Value>
          </Filter>
          <Filter ignoreCase="true" operation="CONTAINS_ALL" property="memberOf">
            <Value>
              <List>
                <String>CN=SG CMA1CS0022 Local Admins,OU=CMCC Ser Local Adm,OU=Groups,OU=CMCC,OU=_CORP,DC=oneadr,DC=net</String>
              </List>
            </Value>
          </Filter>
          <Filter ignoreCase="true" operation="CONTAINS_ALL" property="memberOf">
            <Value>
              <List>
                <String>CN=SG CMA1CS0020 Local Admins,OU=CMCC Ser Local Adm,OU=Groups,OU=CMCC,OU=_CORP,DC=oneadr,DC=net</String>
              </List>
            </Value>
          </Filter>
          <Filter ignoreCase="true" operation="CONTAINS_ALL" property="memberOf">
            <Value>
              <List>
                <String>CN=SG CMA1CS0044 Local Admins,OU=CMCC Ser Local Adm,OU=Groups,OU=CMCC,OU=_CORP,DC=oneadr,DC=net</String>
              </List>
            </Value>
          </Filter>
          <Filter ignoreCase="true" operation="CONTAINS_ALL" property="memberOf">
            <Value>
              <List>
                <String>CN=SG CMA1CS0011 Local Admins,OU=CMCC Ser Local Adm,OU=Groups,OU=CMCC,OU=_CORP,DC=oneadr,DC=net</String>
              </List>
            </Value>
          </Filter>
          <Filter ignoreCase="true" operation="CONTAINS_ALL" property="memberOf">
            <Value>
              <List>
                <String>CN=SG CMA1CS0023 Local Admins,OU=CMCC Ser Local Adm,OU=Groups,OU=CMCC,OU=_CORP,DC=oneadr,DC=net</String>
              </List>
            </Value>
          </Filter>
          <Filter ignoreCase="true" operation="CONTAINS_ALL" property="memberOf">
            <Value>
              <List>
                <String>CN=SG CMA1CS0004 Local Admins,OU=CMCC Ser Local Adm,OU=Groups,OU=CMCC,OU=_CORP,DC=oneadr,DC=net</String>
              </List>
            </Value>
          </Filter>
          <Filter ignoreCase="true" operation="CONTAINS_ALL" property="memberOf">
            <Value>
              <List>
                <String>CN=SG CMA1CS0006 Local Admins,OU=CMCC Ser Local Adm,OU=Groups,OU=CMCC,OU=_CORP,DC=oneadr,DC=net</String>
              </List>
            </Value>
          </Filter>
          <Filter ignoreCase="true" operation="CONTAINS_ALL" property="memberOf">
            <Value>
              <List>
                <String>CN=SG CMA1CS0014 Local Admins,OU=CMCC Ser Local Adm,OU=Groups,OU=CMCC,OU=_CORP,DC=oneadr,DC=net</String>
              </List>
            </Value>
          </Filter>
          <Filter ignoreCase="true" operation="CONTAINS_ALL" property="memberOf">
            <Value>
              <List>
                <String>CN=SG CMA1CS0018 Local Admins,OU=CMCC Ser Local Adm,OU=Groups,OU=CMCC,OU=_CORP,DC=oneadr,DC=net</String>
              </List>
            </Value>
          </Filter>
          <Filter ignoreCase="true" operation="CONTAINS_ALL" property="memberOf">
            <Value>
              <List>
                <String>CN=SG CMA1CS0021 Local Admins,OU=CMCC Ser Local Adm,OU=Groups,OU=CMCC,OU=_CORP,DC=oneadr,DC=net</String>
              </List>
            </Value>
          </Filter>
          <Filter ignoreCase="true" operation="CONTAINS_ALL" property="memberOf">
            <Value>
              <List>
                <String>CN=SG CMA1CS0016 Local Admins,OU=CMCC Ser Local Adm,OU=Groups,OU=CMCC,OU=_CORP,DC=oneadr,DC=net</String>
              </List>
            </Value>
          </Filter>
          <Filter ignoreCase="true" operation="CONTAINS_ALL" property="memberOf">
            <Value>
              <List>
                <String>CN=SG CMA1CS0008 Local Admins,OU=CMCC Ser Local Adm,OU=Groups,OU=CMCC,OU=_CORP,DC=oneadr,DC=net</String>
              </List>
            </Value>
          </Filter>
          <Filter ignoreCase="true" operation="CONTAINS_ALL" property="memberOf">
            <Value>
              <List>
                <String>CN=SG CMA1CS0167 Local Admins,OU=CMCC Ser Local Adm,OU=Groups,OU=CMCC,OU=_CORP,DC=oneadr,DC=net</String>
              </List>
            </Value>
          </Filter>
          <Filter ignoreCase="true" operation="CONTAINS_ALL" property="memberOf">
            <Value>
              <List>
                <String>CN=SG CMA1CS0151 Local Admins,OU=CMCC Ser Local Adm,OU=Groups,OU=CMCC,OU=_CORP,DC=oneadr,DC=net</String>
              </List>
            </Value>
          </Filter>
          <Filter ignoreCase="true" operation="CONTAINS_ALL" property="memberOf">
            <Value>
              <List>
                <String>CN=SG CMA1CS0051 Local Admins,OU=CMCC Ser Local Adm,OU=Groups,OU=CMCC,OU=_CORP,DC=oneadr,DC=net</String>
              </List>
            </Value>
          </Filter>
          <Filter ignoreCase="true" operation="CONTAINS_ALL" property="memberOf">
            <Value>
              <List>
                <String>CN=SG CMA1CS0091 Local admins,OU=CMCC Ser Local Adm,OU=Groups,OU=CMCC,OU=_CORP,DC=oneadr,DC=net</String>
              </List>
            </Value>
          </Filter>
          <Filter ignoreCase="true" operation="CONTAINS_ALL" property="memberOf">
            <Value>
              <List>
                <String>CN=SG CMA1CS0163 Local Admins,OU=CMCC Ser Local Adm,OU=Groups,OU=CMCC,OU=_CORP,DC=oneadr,DC=net</String>
              </List>
            </Value>
          </Filter>
          <Filter ignoreCase="true" operation="CONTAINS_ALL" property="memberOf">
            <Value>
              <List>
                <String>CN=SG CMA1CS0161 Local Admins,OU=CMCC Ser Local Adm,OU=Groups,OU=CMCC,OU=_CORP,DC=oneadr,DC=net</String>
              </List>
            </Value>
          </Filter>
          <Filter ignoreCase="true" operation="CONTAINS_ALL" property="memberOf">
            <Value>
              <List>
                <String>CN=SG CMA1CS0047 Local Admins,OU=CMCC Ser Local Adm,OU=Groups,OU=CMCC,OU=_CORP,DC=oneadr,DC=net</String>
              </List>
            </Value>
          </Filter>
          <Filter ignoreCase="true" operation="CONTAINS_ALL" property="memberOf">
            <Value>
              <List>
                <String>CN=SG CMA1CS0046 Local Admins,OU=CMCC Ser Local Adm,OU=Groups,OU=CMCC,OU=_CORP,DC=oneadr,DC=net</String>
              </List>
            </Value>
          </Filter>
          <Filter ignoreCase="true" operation="CONTAINS_ALL" property="memberOf">
            <Value>
              <List>
                <String>CN=SG CMA1CS0168 Local Admins,OU=CMCC Ser Local Adm,OU=Groups,OU=CMCC,OU=_CORP,DC=oneadr,DC=net</String>
              </List>
            </Value>
          </Filter>
          <Filter ignoreCase="true" operation="CONTAINS_ALL" property="memberOf">
            <Value>
              <List>
                <String>CN=SG CMA1CS0158 Local Admins,OU=CMCC Ser Local Adm,OU=Groups,OU=CMCC,OU=_CORP,DC=oneadr,DC=net</String>
              </List>
            </Value>
          </Filter>
          <Filter ignoreCase="true" operation="CONTAINS_ALL" property="memberOf">
            <Value>
              <List>
                <String>CN=SG CMA1CS0054 Local Admins,OU=CMCC Ser Local Adm,OU=Groups,OU=CMCC,OU=_CORP,DC=oneadr,DC=net</String>
              </List>
            </Value>
          </Filter>
          <Filter ignoreCase="true" operation="CONTAINS_ALL" property="memberOf">
            <Value>
              <List>
                <String>CN=SG CMA1CS0056 Local Admins,OU=CMCC Ser Local Adm,OU=Groups,OU=CMCC,OU=_CORP,DC=oneadr,DC=net</String>
              </List>
            </Value>
          </Filter>
          <Filter ignoreCase="true" operation="CONTAINS_ALL" property="memberOf">
            <Value>
              <List>
                <String>CN=SG CMA1CS0155 Local Admins,OU=CMCC Ser Local Adm,OU=Groups,OU=CMCC,OU=_CORP,DC=oneadr,DC=net</String>
              </List>
            </Value>
          </Filter>
          <Filter ignoreCase="true" operation="CONTAINS_ALL" property="memberOf">
            <Value>
              <List>
                <String>CN=SG CMA1CS0152 Local Admins,OU=CMCC Ser Local Adm,OU=Groups,OU=CMCC,OU=_CORP,DC=oneadr,DC=net</String>
              </List>
            </Value>
          </Filter>
          <Filter ignoreCase="true" operation="CONTAINS_ALL" property="memberOf">
            <Value>
              <List>
                <String>CN=SG CMA1CS0153 Local Admins,OU=CMCC Ser Local Adm,OU=Groups,OU=CMCC,OU=_CORP,DC=oneadr,DC=net</String>
              </List>
            </Value>
          </Filter>
          <Filter ignoreCase="true" operation="CONTAINS_ALL" property="memberOf">
            <Value>
              <List>
                <String>CN=SG CMA1CS0157 Local Admins,OU=CMCC Ser Local Adm,OU=Groups,OU=CMCC,OU=_CORP,DC=oneadr,DC=net</String>
              </List>
            </Value>
          </Filter>
          <Filter ignoreCase="true" operation="CONTAINS_ALL" property="memberOf">
            <Value>
              <List>
                <String>CN=SG CMA1CS011 Local Admins,OU=CMCC Ser Local Adm,OU=Groups,OU=CMCC,OU=_CORP,DC=oneadr,DC=net</String>
              </List>
            </Value>
          </Filter>
          <Filter ignoreCase="true" operation="CONTAINS_ALL" property="memberOf">
            <Value>
              <List>
                <String>CN=SG CMA1CS0160 Local Admins,OU=CMCC Ser Local Adm,OU=Groups,OU=CMCC,OU=_CORP,DC=oneadr,DC=net</String>
              </List>
            </Value>
          </Filter>
          <Filter ignoreCase="true" operation="CONTAINS_ALL" property="memberOf">
            <Value>
              <List>
                <String>CN=SG CMA1CS0154 Local Admins,OU=CMCC Ser Local Adm,OU=Groups,OU=CMCC,OU=_CORP,DC=oneadr,DC=net</String>
              </List>
            </Value>
          </Filter>
          <Filter ignoreCase="true" operation="CONTAINS_ALL" property="memberOf">
            <Value>
              <List>
                <String>CN=SG CMA1CS0057 Local admins,OU=CMCC Ser Local Adm,OU=Groups,OU=CMCC,OU=_CORP,DC=oneadr,DC=net</String>
              </List>
            </Value>
          </Filter>
          <Filter ignoreCase="true" operation="CONTAINS_ALL" property="memberOf">
            <Value>
              <List>
                <String>CN=SG CMA1CS0049 Local Admins,OU=CMCC Ser Local Adm,OU=Groups,OU=CMCC,OU=_CORP,DC=oneadr,DC=net</String>
              </List>
            </Value>
          </Filter>
          <Filter ignoreCase="true" operation="CONTAINS_ALL" property="memberOf">
            <Value>
              <List>
                <String>CN=SG CMA1CS0156 Local Admins,OU=CMCC Ser Local Adm,OU=Groups,OU=CMCC,OU=_CORP,DC=oneadr,DC=net</String>
              </List>
            </Value>
          </Filter>
          <Filter ignoreCase="true" operation="CONTAINS_ALL" property="memberOf">
            <Value>
              <List>
                <String>CN=SG CMA1CS0055 Local Admins,OU=CMCC Ser Local Adm,OU=Groups,OU=CMCC,OU=_CORP,DC=oneadr,DC=net</String>
              </List>
            </Value>
          </Filter>
          <Filter ignoreCase="true" operation="CONTAINS_ALL" property="memberOf">
            <Value>
              <List>
                <String>CN=SG CMA1CS0159 Local Admins,OU=CMCC Ser Local Adm,OU=Groups,OU=CMCC,OU=_CORP,DC=oneadr,DC=net</String>
              </List>
            </Value>
          </Filter>
          <Filter ignoreCase="true" operation="CONTAINS_ALL" property="memberOf">
            <Value>
              <List>
                <String>CN=SG CMA1CS0048 Local Admins,OU=CMCC Ser Local Adm,OU=Groups,OU=CMCC,OU=_CORP,DC=oneadr,DC=net</String>
              </List>
            </Value>
          </Filter>
          <Filter ignoreCase="true" operation="CONTAINS_ALL" property="memberOf">
            <Value>
              <List>
                <String>CN=SG CMA1CS0045 Local Admins,OU=CMCC Ser Local Adm,OU=Groups,OU=CMCC,OU=_CORP,DC=oneadr,DC=net</String>
              </List>
            </Value>
          </Filter>
          <Filter ignoreCase="true" operation="CONTAINS_ALL" property="memberOf">
            <Value>
              <List>
                <String>CN=SG CMA1CS0126 Local Admins,OU=CMCC Ser Local Adm,OU=Groups,OU=CMCC,OU=_CORP,DC=oneadr,DC=net</String>
              </List>
            </Value>
          </Filter>
          <Filter ignoreCase="true" operation="CONTAINS_ALL" property="memberOf">
            <Value>
              <List>
                <String>CN=SG CMA1CS0137 Local Admins,OU=CMCC Ser Local Adm,OU=Groups,OU=CMCC,OU=_CORP,DC=oneadr,DC=net</String>
              </List>
            </Value>
          </Filter>
          <Filter ignoreCase="true" operation="CONTAINS_ALL" property="memberOf">
            <Value>
              <List>
                <String>CN=SG CMA1CS0162 Local Admins,OU=CMCC Ser Local Adm,OU=Groups,OU=CMCC,OU=_CORP,DC=oneadr,DC=net</String>
              </List>
            </Value>
          </Filter>
          <Filter ignoreCase="true" operation="CONTAINS_ALL" property="memberOf">
            <Value>
              <List>
                <String>CN=SG CMA1CS0177 Local Admins,OU=CMCC Ser Local Adm,OU=Groups,OU=CMCC,OU=_CORP,DC=oneadr,DC=net</String>
              </List>
            </Value>
          </Filter>
          <Filter ignoreCase="true" operation="CONTAINS_ALL" property="memberOf">
            <Value>
              <List>
                <String>CN=SG CMA1CS0197 Local Admin,OU=CMCC Ser Local Adm,OU=Groups,OU=CMCC,OU=_CORP,DC=oneadr,DC=net</String>
              </List>
            </Value>
          </Filter>
          <Filter ignoreCase="true" operation="CONTAINS_ALL" property="memberOf">
            <Value>
              <List>
                <String>CN=SG CMA1CS0207 Local Admins,OU=CMCC Ser Local Adm,OU=Groups,OU=CMCC,OU=_CORP,DC=oneadr,DC=net</String>
              </List>
            </Value>
          </Filter>
          <Filter ignoreCase="true" operation="CONTAINS_ALL" property="memberOf">
            <Value>
              <List>
                <String>CN=SG CMA1CS0210 Local Admins,OU=CMCC Ser Local Adm,OU=Groups,OU=CMCC,OU=_CORP,DC=oneadr,DC=net</String>
              </List>
            </Value>
          </Filter>
          <Filter ignoreCase="true" operation="CONTAINS_ALL" property="memberOf">
            <Value>
              <List>
                <String>CN=SG CMA1CS0192 Local Admin,OU=CMCC Ser Local Adm,OU=Groups,OU=CMCC,OU=_CORP,DC=oneadr,DC=net</String>
              </List>
            </Value>
          </Filter>
          <Filter ignoreCase="true" operation="CONTAINS_ALL" property="memberOf">
            <Value>
              <List>
                <String>CN=SG CMA1CS0170 Local Admins,OU=CMCC Ser Local Adm,OU=Groups,OU=CMCC,OU=_CORP,DC=oneadr,DC=net</String>
              </List>
            </Value>
          </Filter>
          <Filter ignoreCase="true" operation="CONTAINS_ALL" property="memberOf">
            <Value>
              <List>
                <String>CN=SG CMA1CS0219 Local Admins,OU=CMCC Ser Local Adm,OU=Groups,OU=CMCC,OU=_CORP,DC=oneadr,DC=net</String>
              </List>
            </Value>
          </Filter>
          <Filter ignoreCase="true" operation="CONTAINS_ALL" property="memberOf">
            <Value>
              <List>
                <String>CN=SG CMA1CS0183 Local Admins,OU=CMCC Ser Local Adm,OU=Groups,OU=CMCC,OU=_CORP,DC=oneadr,DC=net</String>
              </List>
            </Value>
          </Filter>
          <Filter ignoreCase="true" operation="CONTAINS_ALL" property="memberOf">
            <Value>
              <List>
                <String>CN=SG CMA1CS0209 Local Admins,OU=CMCC Ser Local Adm,OU=Groups,OU=CMCC,OU=_CORP,DC=oneadr,DC=net</String>
              </List>
            </Value>
          </Filter>
          <Filter ignoreCase="true" operation="CONTAINS_ALL" property="memberOf">
            <Value>
              <List>
                <String>CN=SG CMA1CS0211 Local Admins,OU=CMCC Ser Local Adm,OU=Groups,OU=CMCC,OU=_CORP,DC=oneadr,DC=net</String>
              </List>
            </Value>
          </Filter>
          <Filter ignoreCase="true" operation="CONTAINS_ALL" property="memberOf">
            <Value>
              <List>
                <String>CN=SG CMA1CS0214 Local Admin,OU=CMCC Ser Local Adm,OU=Groups,OU=CMCC,OU=_CORP,DC=oneadr,DC=net</String>
              </List>
            </Value>
          </Filter>
          <Filter ignoreCase="true" operation="CONTAINS_ALL" property="memberOf">
            <Value>
              <List>
                <String>CN=SG CMA1CS0212 Local Admins,OU=CMCC Ser Local Adm,OU=Groups,OU=CMCC,OU=_CORP,DC=oneadr,DC=net</String>
              </List>
            </Value>
          </Filter>
          <Filter ignoreCase="true" operation="CONTAINS_ALL" property="memberOf">
            <Value>
              <List>
                <String>CN=SG CMA1CS0206 Local Admins,OU=CMCC Ser Local Adm,OU=Groups,OU=CMCC,OU=_CORP,DC=oneadr,DC=net</String>
              </List>
            </Value>
          </Filter>
          <Filter ignoreCase="true" operation="CONTAINS_ALL" property="memberOf">
            <Value>
              <List>
                <String>CN=SG CMA1CS0191 Local Admins,OU=CMCC Ser Local Adm,OU=Groups,OU=CMCC,OU=_CORP,DC=oneadr,DC=net</String>
              </List>
            </Value>
          </Filter>
          <Filter ignoreCase="true" operation="CONTAINS_ALL" property="memberOf">
            <Value>
              <List>
                <String>CN=SG CMA1CS0215 Local Admins,OU=CMCC Ser Local Adm,OU=Groups,OU=CMCC,OU=_CORP,DC=oneadr,DC=net</String>
              </List>
            </Value>
          </Filter>
          <Filter ignoreCase="true" operation="CONTAINS_ALL" property="memberOf">
            <Value>
              <List>
                <String>CN=SG CMA1CS0198 Local Admin,OU=CMCC Ser Local Adm,OU=Groups,OU=CMCC,OU=_CORP,DC=oneadr,DC=net</String>
              </List>
            </Value>
          </Filter>
          <Filter ignoreCase="true" operation="CONTAINS_ALL" property="memberOf">
            <Value>
              <List>
                <String>CN=SG CMA1CS0193 Local Admin,OU=CMCC Ser Local Adm,OU=Groups,OU=CMCC,OU=_CORP,DC=oneadr,DC=net</String>
              </List>
            </Value>
          </Filter>
          <Filter ignoreCase="true" operation="CONTAINS_ALL" property="memberOf">
            <Value>
              <List>
                <String>CN=SG CMA1CS0196 Local Admins,OU=CMCC Ser Local Adm,OU=Groups,OU=CMCC,OU=_CORP,DC=oneadr,DC=net</String>
              </List>
            </Value>
          </Filter>
          <Filter ignoreCase="true" operation="CONTAINS_ALL" property="memberOf">
            <Value>
              <List>
                <String>CN=SG CMA1CS0208 Local Admins,OU=CMCC Ser Local Adm,OU=Groups,OU=CMCC,OU=_CORP,DC=oneadr,DC=net</String>
              </List>
            </Value>
          </Filter>
          <Filter ignoreCase="true" operation="CONTAINS_ALL" property="memberOf">
            <Value>
              <List>
                <String>CN=SG CMA1CS0190 Local Admins,OU=CMCC Ser Local Adm,OU=Groups,OU=CMCC,OU=_CORP,DC=oneadr,DC=net</String>
              </List>
            </Value>
          </Filter>
          <Filter ignoreCase="true" operation="CONTAINS_ALL" property="memberOf">
            <Value>
              <List>
                <String>CN=SG CMA1CS0178 Local Admins,OU=CMCC Ser Local Adm,OU=Groups,OU=CMCC,OU=_CORP,DC=oneadr,DC=net</String>
              </List>
            </Value>
          </Filter>
          <Filter ignoreCase="true" operation="CONTAINS_ALL" property="memberOf">
            <Value>
              <List>
                <String>CN=SG CMA1CS0213 Local Admins,OU=CMCC Ser Local Adm,OU=Groups,OU=CMCC,OU=_CORP,DC=oneadr,DC=net</String>
              </List>
            </Value>
          </Filter>
          <Filter ignoreCase="true" operation="CONTAINS_ALL" property="memberOf">
            <Value>
              <List>
                <String>CN=SG CMA1CS0169 Local Admins,OU=CMCC Ser Local Adm,OU=Groups,OU=CMCC,OU=_CORP,DC=oneadr,DC=net</String>
              </List>
            </Value>
          </Filter>
          <Filter ignoreCase="true" operation="CONTAINS_ALL" property="memberOf">
            <Value>
              <List>
                <String>CN=SG CMA1CS0179 Local Admins,OU=CMCC Ser Local Adm,OU=Groups,OU=CMCC,OU=_CORP,DC=oneadr,DC=net</String>
              </List>
            </Value>
          </Filter>
          <Filter ignoreCase="true" operation="CONTAINS_ALL" property="memberOf">
            <Value>
              <List>
                <String>CN=SG CMA1CS0181 Local Admins,OU=CMCC Ser Local Adm,OU=Groups,OU=CMCC,OU=_CORP,DC=oneadr,DC=net</String>
              </List>
            </Value>
          </Filter>
          <Filter ignoreCase="true" operation="CONTAINS_ALL" property="memberOf">
            <Value>
              <List>
                <String>CN=SG CMA1CS0180 Local Admins,OU=CMCC Ser Local Adm,OU=Groups,OU=CMCC,OU=_CORP,DC=oneadr,DC=net</String>
              </List>
            </Value>
          </Filter>
          <Filter ignoreCase="true" operation="CONTAINS_ALL" property="memberOf">
            <Value>
              <List>
                <String>CN=SG CMA1CS0182 Local Admins,OU=CMCC Ser Local Adm,OU=Groups,OU=CMCC,OU=_CORP,DC=oneadr,DC=net</String>
              </List>
            </Value>
          </Filter>
          <Filter ignoreCase="true" operation="CONTAINS_ALL" property="memberOf">
            <Value>
              <List>
                <String>CN=SG CMA1CS0273 Local Admins,OU=Migrated Groups,OU=Groups,OU=DK,OU=_CORP,DC=oneadr,DC=net</String>
              </List>
            </Value>
          </Filter>
          <Filter ignoreCase="true" operation="CONTAINS_ALL" property="memberOf">
            <Value>
              <List>
                <String>CN=SG CMA1CS0274 Local Admins,OU=Migrated Groups,OU=Groups,OU=DK,OU=_CORP,DC=oneadr,DC=net</String>
              </List>
            </Value>
          </Filter>
          <Filter ignoreCase="true" operation="CONTAINS_ALL" property="memberOf">
            <Value>
              <List>
                <String>CN=SG CMA1CS0275 Local Admins,OU=Migrated Groups,OU=Groups,OU=DK,OU=_CORP,DC=oneadr,DC=net</String>
              </List>
            </Value>
          </Filter>
          <Filter ignoreCase="true" operation="CONTAINS_ALL" property="memberOf">
            <Value>
              <List>
                <String>CN=SG CMA1CS0276 Local Admins,OU=Migrated Groups,OU=Groups,OU=DK,OU=_CORP,DC=oneadr,DC=net</String>
              </List>
            </Value>
          </Filter>
          <Filter ignoreCase="true" operation="CONTAINS_ALL" property="memberOf">
            <Value>
              <List>
                <String>CN=SG CMA1CS0277 Local Admins,OU=Migrated Groups,OU=Groups,OU=DK,OU=_CORP,DC=oneadr,DC=net</String>
              </List>
            </Value>
          </Filter>
          <Filter ignoreCase="true" operation="CONTAINS_ALL" property="memberOf">
            <Value>
              <List>
                <String>CN=SG CMA1CS0278 Local Admins,OU=Migrated Groups,OU=Groups,OU=DK,OU=_CORP,DC=oneadr,DC=net</String>
              </List>
            </Value>
          </Filter>
          <Filter ignoreCase="true" operation="CONTAINS_ALL" property="memberOf">
            <Value>
              <List>
                <String>CN=SG CMA1CS0279 Local Admins,OU=Migrated Groups,OU=Groups,OU=DK,OU=_CORP,DC=oneadr,DC=net</String>
              </List>
            </Value>
          </Filter>
          <Filter ignoreCase="true" operation="CONTAINS_ALL" property="memberOf">
            <Value>
              <List>
                <String>CN=SG CMA1CS0280 Local Admins,OU=Migrated Groups,OU=Groups,OU=DK,OU=_CORP,DC=oneadr,DC=net</String>
              </List>
            </Value>
          </Filter>
          <Filter ignoreCase="true" operation="CONTAINS_ALL" property="memberOf">
            <Value>
              <List>
                <String>CN=SG CMA1CS0281 Local Admins,OU=Migrated Groups,OU=Groups,OU=DK,OU=_CORP,DC=oneadr,DC=net</String>
              </List>
            </Value>
          </Filter>
          <Filter ignoreCase="true" operation="CONTAINS_ALL" property="memberOf">
            <Value>
              <List>
                <String>CN=SG DKA1CS0173 Lokal Admins,OU=MGR_Groups,OU=Migrated Groups,OU=Groups,OU=DK,OU=_CORP,DC=oneadr,DC=net</String>
              </List>
            </Value>
          </Filter>
          <Filter ignoreCase="true" operation="CONTAINS_ALL" property="memberOf">
            <Value>
              <List>
                <String>CN=SG DKA1CS0174 Lokal Admins,OU=MGR_Groups,OU=Migrated Groups,OU=Groups,OU=DK,OU=_CORP,DC=oneadr,DC=net</String>
              </List>
            </Value>
          </Filter>
        </CompositeFilter>
      </Constraints>
    </Profile>
  </Profiles>
</Bundle>
